{
    "Added": "נוסף",
    "ApiKeyValidationHealthCheckMessage": "עדכן בבקשה את מפתח ה־API שלך כדי שיהיה באורך של לפחות {0} תווים. תוכל לעשות זאת בהגדרות או דרך קובץ הקונפיגורציה.",
    "About": "אודות",
    "Actions": "פעולות",
    "Language": "שפה",
    "BackupFolderHelpText": "נתיבים יחסית יהיו תחת ספריית AppData של {appName}",
    "Small": "קָטָן",
    "StartProcessing": "התחל לעבד",
    "Tags": "תגים",
    "Updates": "עדכונים",
    "UseHardlinksInsteadOfCopy": "השתמש בקישורים קשיחים במקום בהעתקה",
    "Indexer": "אינדקסר",
    "Queued": "בתור",
    "Refresh": "לְרַעֲנֵן",
    "RelativePath": "נתיב יחסי",
    "Reload": "לִטעוֹן מִחָדָשׁ",
    "MonitoredStatus": "פיקוח / סטטוס",
    "Month": "חוֹדֶשׁ",
    "More": "יותר",
    "MoreDetails": "פרטים נוספים",
    "MoreInfo": "עוד מידע",
    "MountHealthCheckMessage": "הר המכיל נתיב סרט מותקן לקריאה בלבד: ",
    "MoveFiles": "העבר קבצים",
    "MoveSiteFoldersDontMoveFiles": "לא, אני אעביר את הקבצים בעצמי",
    "MoveSiteFoldersMoveFiles": "כן, העבר את הקבצים",
    "AllSitesAreHiddenByTheAppliedFilter": "כל התוצאות מוסתרות על ידי המסנן שהוחל",
    "AlternateTitles": "כותרת חלופית",
    "DeleteIndexer": "מחק את אינדקס",
    "DeleteIndexerMessageText": "האם אתה בטוח שברצונך למחוק את פרופיל האיכות {0}",
    "DeleteNotification": "מחק הודעה",
    "DeleteQualityProfile": "מחק פרופיל איכות",
    "EnableAutomaticAdd": "אפשר הוספה אוטומטית",
    "EnableAutomaticSearchHelpTextWarning": "ישמש כאשר נעשה שימוש בחיפוש אינטראקטיבי",
    "EnableColorImpairedMode": "אפשר מצב של פגיעה בצבע",
    "FailedToLoadTagsFromApi": "טעינת הסרט נכשלה מה- API נכשלה",
    "FeatureRequests": "בקשות תכונה",
    "FileManagement": "ניהול קבצים",
    "FileNameTokens": "אסימונים לשם קובץ",
    "Filename": "שם קובץ",
    "Activity": "פעילות",
    "Add": "הוסף",
    "AddNew": "הוסף חדש",
    "Name": "שֵׁם",
    "FormatAgeHours": "שעה (ות",
    "FormatAgeMinute": "דקות",
    "FormatAgeMinutes": "דקות",
    "AddListExclusionError": "לא ניתן להוסיף אי הכללה ברשימה חדשה, נסה שוב.",
    "AddNewRestriction": "הוסף הגבלה חדשה",
    "AddNewSiteError": "טעינת תוצאות החיפוש נכשלה, נסה שוב.",
    "AddNewSiteHelpText": "קל להוסיף סרט חדש, פשוט התחל להקליד את שם הסרט שתרצה להוסיף",
    "AddingTag": "מוסיף תג",
    "AllFiles": "כל הקבצים",
    "AutomaticSearch": "חיפוש אוטומטי",
    "BackupIntervalHelpText": "מרווח בין גיבויים אוטומטיים",
    "BackupsLoadError": "לא ניתן לטעון גיבויים",
    "Branch": "ענף",
    "CheckDownloadClientForDetails": "בדוק את לקוח ההורדות לפרטים נוספים",
    "ChownGroupHelpText": "שם הקבוצה או ה- gid. השתמש ב- gid עבור מערכות קבצים מרוחקות.",
    "ClickToChangeYear": "לחץ כדי לשנות סרט",
    "DisabledForLocalAddresses": "מושבת לכתובות מקומיות",
    "EnableHelpText": "אפשר יצירת קובץ מטא-נתונים עבור סוג מטא-נתונים זה",
    "EnableSsl": "אפשר SSL",
    "Events": "אירועים",
    "Failed": "נִכשָׁל",
    "FileBrowserPlaceholderText": "התחל להקליד או בחר נתיב למטה",
    "FirstDayOfWeek": "היום הראשון בשבוע",
    "ICalLink": "קישור ל- iCal",
    "Age": "גיל",
    "All": "הכל",
    "AnalyseVideoFilesHelpText": "חלץ מידע וידאו כגון רזולוציה, זמן ריצה ומידע קודק מקבצים. זה מחייב את {appName} לקרוא חלקים מהקובץ שעלולים לגרום לדיסק גבוה או לפעילות רשת במהלך הסריקות.",
    "ApiKey": "מפתח API",
    "Apply": "להגיש מועמדות",
    "Automatic": "אוֹטוֹמָטִי",
    "BeforeUpdate": "לפני העדכון",
    "BindAddress": "כתובת איגוד",
    "BindAddressHelpText": "יש להזין localhost, כתובת IP או '*' כדי לאפשר הכל",
    "Blocklist": "רשימה שחורה",
    "BranchUpdate": "ענף לשימוש עדכון {appName}",
    "BranchUpdateMechanism": "ענף המשמש את מנגנון העדכון החיצוני",
    "Calendar": "לוּחַ שָׁנָה",
    "CalendarFeed": "עדכון לוח השנה של {appName}",
    "CalendarOptions": "אפשרויות לוח שנה",
    "CalendarLoadError": "לא ניתן לטעון את היומן",
    "CancelPendingTask": "האם אתה בטוח שברצונך לבטל משימה זו בהמתנה?",
    "CancelProcessing": "בטל עיבוד",
    "CertificateValidation": "אימות תעודה",
    "Certification": "תעודה",
    "ChangeFileDate": "שנה את תאריך הקובץ",
    "ChangeFileDateHelpText": "שנה את תאריך הקובץ בעת הייבוא / סריקה מחדש",
    "ChmodFolder": "תיקיית chmod",
    "ChmodFolderHelpText": "אוקטאל, מוחל במהלך ייבוא / שינוי שם לתיקיות מדיה וקבצים (ללא סיביות ביצוע)",
    "ChmodFolderHelpTextWarning": "זה עובד רק אם המשתמש שמפעיל את {appName} הוא הבעלים של הקובץ. עדיף לוודא שלקוח ההורדה מגדיר את ההרשאות כהלכה.",
    "ChooseAnotherFolder": "בחר תיקיה אחרת",
    "ClickToChangeLanguage": "לחץ כדי לשנות שפה",
    "ClickToChangeQuality": "לחץ כדי לשנות את האיכות",
    "ClickToChangeReleaseGroup": "לחץ כדי לשנות קבוצת שחרור",
    "ConnectionLost": "החיבור אבד",
    "ConnectionLostReconnect": "Radarr ינסה להתחבר אוטומטית, או שתלחץ על טען מחדש למטה.",
    "CustomFilters": "מסננים מותאמים אישית",
    "CustomFormatScore": "ציון פורמט מותאם אישית",
    "DelayProfileTagsHelpText": "חל על סרטים עם תג אחד לפחות תואם",
    "DelayProfiles": "עיכוב פרופילים",
    "DelayProfilesLoadError": "לא ניתן לטעון פרופילי עיכוב",
    "DelayingDownloadUntil": "מעכב את ההורדה עד {0} בשעה {1}",
    "Delete": "לִמְחוֹק",
    "DeleteBackupMessageText": "האם אתה בטוח שברצונך למחוק את פרופיל האיכות {0}",
    "DeleteCustomFormat": "מחק פורמט מותאם אישית",
    "DeleteDelayProfile": "מחק פרופיל עיכוב",
    "DeleteDelayProfileMessageText": "האם אתה בטוח שברצונך למחוק פרופיל עיכוב זה?",
    "DeleteDownloadClient": "מחק את לקוח ההורדות",
    "DeleteEpisodeFileMessage": "האם למחוק את {0}?",
    "DeleteRemotePathMappingMessageText": "האם אתה בטוח שברצונך למחוק את מיפוי הנתיבים המרוחק הזה?",
    "DeleteSelectedDownloadClients": "מחק את לקוח ההורדות",
    "DeleteSelectedEpisodeFilesHelpText": "האם אתה בטוח שברצונך למחוק את קבצי הסרט שנבחרו?",
    "DeleteTag": "מחק את התג",
    "DeleteTagMessageText": "האם אתה בטוח שברצונך למחוק את התג '{0}'?",
    "Deleted": "נמחק",
    "DeletedReasonMissingFromDisk": "Whisparr לא הצליח למצוא את הקובץ בדיסק ולכן הוא הוסר",
    "DeletedReasonUpgrade": "הקובץ נמחק כדי לייבא שדרוג",
    "DestinationPath": "נתיב יעד",
    "DestinationRelativePath": "מסלול יחסי יעד",
    "Details": "פרטים",
    "File": "קבצים",
    "Folders": "תיקיות",
    "ImportMechanismHandlingDisabledHealthCheckMessage": "אפשר טיפול בהורדות שהושלם",
    "InteractiveImportLoadError": "לא ניתן לטעון פריטי ייבוא ידניים",
    "MinimumLimits": "מגבלות מינימום",
    "MonitoredOnly": "מנוטר בלבד",
    "QualitySettings": "הגדרות איכות",
    "NoIssuesWithYourConfiguration": "אין בעיות בתצורה שלך",
    "None": "אף אחד",
    "PendingChangesStayReview": "הישאר וסקר שינויים",
    "Preferred": "מועדף",
    "Queue": "תוֹר",
    "StartImport": "התחל לייבא",
    "TableColumnsHelpText": "בחר אילו עמודות גלויות ובאיזה סדר הן יופיעו",
    "TableOptions": "אפשרויות טבלה",
    "UiLanguage": "שפת ממשק משתמש",
    "UnableToLoadBackups": "לא ניתן לטעון גיבויים",
    "AddAutoTag": "הוסף טגית אוטומטית",
    "AddRootFolder": "הוסף תיקיית שורש",
    "AudioInfo": "מידע שמע",
    "Backup": "גיבוי",
    "BlocklistReleases": "שחרור הרשימה השחורה",
    "Duration": "אורך",
    "Edit": "לַעֲרוֹך",
    "NoLeaveIt": "לא, עזוב את זה",
    "Unavailable": "אינו זמין",
    "DownloadClients": "הורד לקוחות",
    "DownloadFailed": "הורדה נכשלה",
    "DownloadPropersAndRepacks": "Propers ו Repacks",
    "DownloadPropersAndRepacksHelpText": "בין אם לשדרג אוטומטית ל- Propers / Repacks",
    "DownloadPropersAndRepacksHelpTextCustomFormat": "השתמש ב'אל תעדיף 'כדי למיין לפי ציון פורמט מותאם אישית על פני Propers / Repacks",
    "Downloaded": "הורד",
    "Downloading": "מוריד",
    "EditCustomFormat": "ערוך פורמט מותאם אישית",
    "Fixed": "תוקן",
    "Host": "מנחה",
    "ICalFeedHelpText": "העתק כתובת URL זו ללקוחות שלך או לחץ כדי להירשם אם הדפדפן שלך תומך ב- webcal",
    "KeyboardShortcuts": "קיצורי דרך במקלדת",
    "KeyboardShortcutsCloseModal": "סגור את המודול הנוכחי",
    "LastWriteTime": "זמן כתיבה אחרון",
    "Level": "רָמָה",
    "LibraryImport": "ייבוא ספרייה",
    "LibraryImportTips": "כמה טיפים להבטחת הייבוא בצורה חלקה:",
    "Links": "קישורים",
    "Manual": "מדריך ל",
    "ManualImport": "ייבוא ידני",
    "Missing": "חָסֵר",
    "MustNotContainHelpText": "המהדורה תידחה אם היא מכילה אחד או יותר מהתנאים (חסר רישיות)",
    "NamingSettings": "הגדרת שמות",
    "NamingSettingsLoadError": "לא ניתן לטעון את הגדרות השמות",
    "Negate": "לִשְׁלוֹל",
    "NegateHelpText": "אם מסומן, הפורמט המותאם אישית לא יחול אם תנאי זה {0} תואם.",
    "Negated": "שלילי",
    "NoLimitForAnyRuntime": "אין הגבלה לכל זמן ריצה",
    "NoLinks": "אין קישורים",
    "OrganizeSelectedSitesModalHeader": "ארגן סרטים נבחרים",
    "Overview": "סקירה כללית",
    "Presets": "הגדרות קבועות מראש",
    "Progress": "התקדמות",
    "Proxy": "פרוקסי",
    "Protocol": "נוהל",
    "ProxyBypassFilterHelpText": "השתמש ב- ',' כמפריד וב- '*.' כתו כללי לתת-דומיינים",
    "ProxyFailedToTestHealthCheckMessage": "נכשל בדיקת ה- proxy: {0}",
    "ProxyPasswordHelpText": "עליך להזין שם משתמש וסיסמה רק אם נדרשים שם. השאר אותם ריקים אחרת.",
    "ProxyType": "סוג proxy",
    "ProxyUsernameHelpText": "עליך להזין שם משתמש וסיסמה רק אם נדרשים שם. השאר אותם ריקים אחרת.",
    "QualityProfiles": "פרופילי איכות",
    "QualityProfilesLoadError": "לא ניתן לטעון פרופילי איכות",
    "QualitySettingsSummary": "מידות איכות ושמות",
    "RefreshAndScan": "רענון וסריקה",
    "RefreshAndScanTooltip": "רענן מידע וסריקת הדיסק",
    "RejectionCount": "ספירת דחייה",
    "Release": "מְשׁוּחרָר",
    "ReleaseTitle": "שחרר את הכותרת",
    "RemotePath": "נתיב מרוחק",
    "RemotePathMappingBadDockerPathHealthCheckMessage": "אתה משתמש בדוקר; קליינט ההורדות {0} שם הורדות ב-{1} אבל הנתיב לא תקין {2}. בחן מחדש את ניתוב התיקיות והגדרות קליינט ההורדות.",
    "RemoveCompletedDownloadsHelpText": "הסר הורדות מיובאות מהיסטוריית הלקוחות להורדה",
    "SelectLanguages": "בחר שפה",
    "SelectQuality": "בחר איכות",
    "ShowTitle": "הראה כותרת",
    "SiteIsUnmonitored": "הסרט אינו מנוטר",
    "Sort": "סוג",
    "SourceTitle": "כותרת מקור",
    "SslCertPasswordHelpText": "סיסמה לקובץ pfx",
    "Table": "שולחן",
    "TableColumns": "עמודות",
    "TagsLoadError": "לא ניתן לטעון תגים",
    "TagsSettingsSummary": "ראה את כל התגים ואופן השימוש בהם. ניתן להסיר תגים שאינם בשימוש",
    "Tasks": "משימות",
    "TestAll": "בדוק הכל",
    "TestAllClients": "בדוק את כל הלקוחות",
    "Tomorrow": "מָחָר",
    "Type": "סוּג",
    "Ui": "ממשק משתמש",
    "UnableToLoadRootFolders": "לא ניתן לטעון תיקיות שורש",
    "UnableToUpdateWhisparrDirectly": "לא ניתן לעדכן את {appName} ישירות,",
    "Ungroup": "בטל קבוצה",
    "Unlimited": "ללא הגבלה",
    "UnmappedFolders": "תיקיות לא ממופות",
    "UnmappedFilesOnly": "קבצים שלא ממופים בלבד",
    "UnmonitoredOnly": "מנוטר בלבד",
    "UpdateAll": "עדכן הכל",
    "UpgradesAllowed": "שדרוגים מותרים",
    "UpgradesAllowedHelpText": "אם תכונות הנכים לא ישודרגו",
    "Uptime": "זמן עבודה",
    "UrlBase": "בסיס URL",
    "UrlBaseHelpText": "לתמיכת proxy הפוכה, ברירת המחדל ריקה",
    "UseProxy": "תשתמש בפרוקסי",
    "UsenetDisabled": "Usenet מושבת",
    "Yesterday": "אתמול",
    "YesCancel": "כן, בטל",
    "RootFolderMultipleMissingHealthCheckMessage": "חסרות מספר תיקיות שורש: {0}",
    "Rss": "RSS",
    "AutoRedownloadFailed": "הורדה נכשלה",
    "Backups": "גיבויים",
    "BypassDelayIfAboveCustomFormatScoreMinimumScore": "ציון פורמט מותאם אישית מינימלי",
    "BypassProxyForLocalAddresses": "עקיפת פרוקסי לכתובות מקומיות",
    "ClickToChangeSite": "לחץ כדי לשנות סרט",
    "Connection": "חיבור",
    "CustomFormats": "פורמטים מותאמים אישית",
    "CustomFormatsLoadError": "לא ניתן לטעון פורמטים מותאמים אישית",
    "CustomFormatsSettings": "הגדרות תבניות מותאמות אישית",
    "CustomFormatsSettingsSummary": "פורמטים והגדרות מותאמים אישית",
    "Cutoff": "לחתוך",
    "CutoffUnmet": "חתך שלא הושג",
    "Database": "מסד נתונים",
    "Date": "תַאֲרִיך",
    "Dates": "תאריכים",
    "Day": "יְוֹם",
    "Debug": "לנפות",
    "DefaultCase": "מקרה ברירת מחדל",
    "DefaultDelayProfile": "זהו פרופיל ברירת המחדל. זה חל על כל הסרטים שאין להם פרופיל מפורש.",
    "DeleteConditionMessageText": "האם אתה בטוח שברצונך למחוק את פרופיל האיכות {0}",
    "DeleteCustomFormatMessageText": "האם אתה בטוח שברצונך למחוק את התג '{0}'?",
    "DeleteImportListExclusionMessageText": "האם אתה בטוח שברצונך למחוק אי הכללה זו של רשימת הייבוא?",
    "DeleteSpecificationHelpText": "האם אתה בטוח שברצונך למחוק את פרופיל האיכות {0}",
    "DetailedProgressBar": "סרגל התקדמות מפורט",
    "DetailedProgressBarHelpText": "הצג טקסט בסרגל ההתקדמות",
    "Disabled": "נָכֶה",
    "DownloadClientCheckNoneAvailableHealthCheckMessage": "אין לקוח להורדה זמין",
    "DownloadClientSettings": "הורד את הגדרות הלקוח",
    "DownloadClientsLoadError": "לא ניתן לטעון לקוחות הורדות",
    "DownloadClientsSettingsSummary": "הורד לקוחות, הורד טיפול ומיפוי נתיבים מרוחק",
    "DownloadPropersAndRepacksHelpTextWarning": "השתמש בפורמטים מותאמים אישית לשדרוגים אוטומטיים ל- Propers / Repacks",
    "EditDelayProfile": "ערוך פרופיל עיכוב",
    "EditGroups": "ערוך קבוצות",
    "EditImportListExclusion": "מחק אי הכללת רשימות ייבוא",
    "EditQualityProfile": "ערוך פרופיל איכות",
    "EditRestriction": "ערוך הגבלה",
    "EditRemotePathMapping": "ערוך מיפוי נתיבים מרחוק",
    "Enable": "לְאַפשֵׁר",
    "EnableAutomaticSearch": "אפשר חיפוש אוטומטי",
    "EnableAutomaticSearchHelpText": "ישמש כאשר חיפושים אוטומטיים מבוצעים דרך ממשק המשתמש או על ידי {appName}",
    "EnableInteractiveSearchHelpTextWarning": "אינדקס זה אינו נתמך בחיפוש",
    "EnableMediaInfoHelpText": "חלץ מידע וידאו כגון רזולוציה, זמן ריצה ומידע קודק מקבצים. זה מחייב את {appName} לקרוא חלקים מהקובץ שעלולים לגרום לדיסק גבוה או לפעילות רשת במהלך הסריקות.",
    "EnableRss": "אפשר RSS",
    "EnableSslHelpText": "דרוש הפעלה מחדש כמנהל כדי להיכנס לתוקף",
    "Enabled": "מופעל",
    "Ended": "הסתיים",
    "EpisodeSearchResultsLoadError": "לא ניתן לטעון תוצאות לחיפוש הסרט הזה. נסה שוב מאוחר יותר",
    "Error": "שְׁגִיאָה",
    "ErrorLoadingContents": "שגיאה בטעינת התוכן",
    "ErrorRestoringBackup": "שגיאה בשחזור הגיבוי",
    "EventType": "סוג אירוע",
    "Exception": "יוצא מן הכלל",
    "Existing": "קיים",
    "ExistingTag": "תג קיים",
    "ExportCustomFormat": "ייצא פורמט מותאם אישית",
    "ExtraFileExtensionsHelpText": "רשימה מופרדת באמצעות פסיקים של קבצים נוספים לייבוא (.nfo יובא כ- nfo-orig)",
    "FailedToLoadSeriesFromApi": "טעינת הסרט נכשלה מה- API נכשלה",
    "FileNames": "שמות קבצים",
    "Files": "קבצים",
    "Filter": "לְסַנֵן",
    "Folder": "תיקיה",
    "Forecast": "תַחֲזִית",
    "Formats": "פורמטים",
    "FreeSpace": "מקום פנוי",
    "General": "כללי",
    "GeneralSettings": "הגדרות כלליות",
    "Genres": "ז'אנרים",
    "Grab": "לִתְפּוֹס",
    "GrabId": "תעודת זהות",
    "GrabRelease": "שחרור תפוס",
    "GrabReleaseMessageText": "רדאר לא הצליח לקבוע לאיזה סרט הסרט הזה נועד. ייתכן ש- {appName} לא תוכל לייבא גרסה זו באופן אוטומטי. האם אתה רוצה לתפוס את '{0}'?",
    "GrabSelected": "תפוס נבחר",
    "Grabbed": "תפס",
    "Health": "בְּרִיאוּת",
    "HideAdvanced": "הסתר מתקדם",
    "History": "הִיסטוֹרִיָה",
    "HistoryLoadError": "לא ניתן לטעון את ההיסטוריה",
    "HomePage": "דף הבית",
    "Hostname": "שם מארח",
    "HttpHttps": "HTTP (S)",
    "ICalFeed": "עדכון iCal",
    "ICalIncludeUnmonitoredHelpText": "כלול סרטים ללא פיקוח בפיד iCal",
    "ICalShowAsAllDayEventsHelpText": "אירועים יופיעו כאירועים כל היום בלוח השנה שלך",
    "IconForCutoffUnmet": "סמל Cutoff Unmet",
    "IconForCutoffUnmetHelpText": "הצג סמל לקבצים כאשר הניתוק לא נענה",
    "ImportListExclusionsLoadError": "לא ניתן לטעון אי הכללות ברשימה",
    "ImportListRootFolderMissingRootHealthCheckMessage": "תיקיית אב חסרה, לא ניתן לעשות ייבוא מרשימה(ות): {0}",
    "ImportListRootFolderMultipleMissingRootsHealthCheckMessage": "מספר תיקיות אב חסרות לייבוא רשימות: {0}",
    "ImportListStatusAllUnavailableHealthCheckMessage": "כל הרשימות אינן זמינות בגלל כשלים",
    "ImportListStatusUnavailableHealthCheckMessage": "רשימות לא זמינות בגלל כשלים: {0}",
    "Imported": "מְיוֹבָּא",
    "ImportedTo": "מיובא אל",
    "Importing": "מייבא",
    "IncludeCustomFormatWhenRenaming": "כלול פורמט מותאם אישית בעת שינוי שם",
    "IndexerLongTermStatusAllUnavailableHealthCheckMessage": "כל האינדקסים אינם זמינים עקב כשלים במשך יותר מ -6 שעות",
    "IndexerSearchNoInteractiveHealthCheckMessage": "אין אינדקסים זמינים כאשר חיפוש אינטראקטיבי מופעל, Radarr לא תספק תוצאות חיפוש אינטראקטיביות",
    "IndexersLoadError": "לא ניתן לטעון אינדקסים",
    "InstanceNameHelpText": "שם מופע בטאב ובשביל שם אפליקציית סיסלוג",
    "InstanceName": "שם מופע",
    "InteractiveImport": "ייבוא אינטראקטיבי",
    "InteractiveSearch": "חיפוש אינטראקטיבי",
    "Interval": "הַפסָקָה",
    "InteractiveSearchModalHeader": "חיפוש אינטראקטיבי",
    "KeyboardShortcutsFocusSearchBox": "תיבת חיפוש פוקוס",
    "KeyboardShortcutsConfirmModal": "קבל את מודל האישור",
    "Large": "גָדוֹל",
    "LastDuration": "lastDuration",
    "LastExecution": "ביצוע אחרון",
    "LastUsed": "נעשה שימוש אחרון",
    "Local": "מְקוֹמִי",
    "ListsLoadError": "לא ניתן לטעון רשימות",
    "LocalPath": "נתיב מקומי",
    "Location": "מקום",
    "LogFiles": "קבצי יומן",
    "LogLevel": "רמת יומן",
    "LogLevelTraceHelpTextWarning": "יש להפעיל רישום מעקב באופן זמני בלבד",
    "Logging": "רישום",
    "LongDateFormat": "פורמט תאריך ארוך",
    "MaintenanceRelease": "שחרור תחזוקה: תיקוני באגים ושיפורים אחרים. לפרטים נוספים, ראה היסטוריית התחייבויות של Github",
    "MarkAsFailed": "סמן ככושל",
    "MarkAsFailedConfirmation": "האם אתה בטוח שברצונך לסמן את '{0}' ככושל?",
    "MaximumLimits": "מגבלות מקסימליות",
    "MaximumSize": "גודל מקסימלי",
    "MediaManagementSettings": "הגדרות ניהול מדיה",
    "MediaManagementSettingsLoadError": "לא ניתן לטעון את הגדרות ניהול המדיה",
    "Medium": "בינוני",
    "MegabytesPerMinute": "מגה-בייט לדקה",
    "Message": "הוֹדָעָה",
    "Metadata": "מטא נתונים",
    "MetadataSettings": "הגדרות מטא נתונים",
    "Min": "דקה",
    "MinimumAge": "גיל מינימום",
    "MinimumFreeSpace": "מינימום מקום פנוי",
    "MinimumFreeSpaceHelpText": "למנוע ייבוא אם הוא ישאיר פחות מכמות שטח דיסק זו פנויה",
    "Mode": "מצב",
    "Monday": "יוֹם שֵׁנִי",
    "Monitor": "צג",
    "Monitored": "מנוטר",
    "MoveAutomatically": "ייבוא מהיר",
    "MustContain": "חייב להכיל",
    "MultiLanguages": "ריבוי שפות",
    "MustContainHelpText": "המהדורה חייבת להכיל לפחות אחד ממונחים אלה (חסר רישיות)",
    "MustNotContain": "אסור להכיל",
    "Never": "אף פעם",
    "New": "חָדָשׁ",
    "NoEventsFound": "לא נמצאו אירועים",
    "NoLogFiles": "אין קבצי יומן",
    "NoMinimumForAnyRuntime": "אין מינימום לכל זמן ריצה",
    "NoHistory": "אין היסטוריה",
    "NoResultsFound": "לא נמצאו תוצאות",
    "NoTagsHaveBeenAddedYet": "עדיין לא נוספו תגים",
    "NoUpdatesAreAvailable": "אין עדכונים זמינים",
    "NotificationStatusAllClientHealthCheckMessage": "כל הרשימות אינן זמינות בגלל כשלים",
    "NotificationStatusSingleClientHealthCheckMessage": "רשימות לא זמינות בגלל כשלים: {0}",
    "NotificationTriggers": "מפעילים התראות",
    "NotificationTriggersHelpText": "בחר איזה אירועים יפעילו את ההתראה הזאת",
    "OnApplicationUpdate": "כשהאפליקציה מעדכנת גרסא",
    "OnEpisodeFileDeleteForUpgrade": "במחיקת קובץ הסרט לצורך שדרוג",
    "Ok": "בסדר",
    "OnGrab": "על לתפוס",
    "OnHealthIssue": "בנושא הבריאות",
    "OnImport": "בייבוא",
    "OnlyTorrent": "רק סיקור",
    "Organize": "לְאַרגֵן",
    "OrganizeLoadError": "שגיאה בטעינת תצוגה מקדימה",
    "Original": "מְקוֹרִי",
    "OverviewOptions": "אפשרויות סקירה כללית",
    "PackageVersion": "גרסת חבילה",
    "Password": "סיסמה",
    "Path": "נָתִיב",
    "Paused": "מושהית",
    "Peers": "עמיתים",
    "Pending": "ממתין ל",
    "PendingChangesMessage": "יש לך שינויים שלא נשמרו, האם אתה בטוח שברצונך לעזוב דף זה?",
    "Permissions": "אישורים",
    "Port": "נמל",
    "PortNumber": "מספר יציאה",
    "PosterOptions": "אפשרויות פוסטר",
    "PosterSize": "גודל פוסטר",
    "PreviewRename": "תצוגה מקדימה של שינוי שם",
    "Priority": "עדיפות",
    "PriorityHelpText": "העדיפו עדיפות למספר לקוחות הורדה. Round-Robin משמש ללקוחות עם אותה עדיפות.",
    "ProxyBadRequestHealthCheckMessage": "נכשל בדיקת ה- proxy. קוד קוד: {0}",
    "ProxyResolveIpHealthCheckMessage": "פתרון כתובת ה- IP עבור מארח ה- Proxy המוגדר {0} נכשל",
    "PublishedDate": "תאריך פרסום",
    "Qualities": "איכויות",
    "QualitiesHelpText": "תכונות גבוהות יותר ברשימה עדיפות יותר. איכויות באותה קבוצה שוות. רק איכויות בדוקות רצויות",
    "QualityCutoffNotMet": "קיצוץ האיכות לא נפגש",
    "QualityDefinitions": "הגדרות איכות",
    "QualityDefinitionsLoadError": "לא ניתן לטעון הגדרות איכות",
    "RecentChanges": "שינויים אחרונים",
    "ReleaseGroups": "קבוצת שחרור",
    "ReleaseProfilesLoadError": "לא ניתן לטעון פרופילי עיכוב",
    "ReleaseRejected": "שחרור נדחה",
    "RemotePathMappingFileRemovedHealthCheckMessage": "הקובץ {0} הוסר תוך כדי התהליך.",
    "RemotePathMappingFilesBadDockerPathHealthCheckMessage": "אתה משתמש בדוקר; קליינט ההורדות {0} שם הורדות ב-{1} אבל הנתיב לא תקין {2}. בחן מחדש את ניתוב התיקיות והגדרות קליינט ההורדות.",
    "RemotePathMappingFilesWrongOSPathHealthCheckMessage": "אתה משתמש בדוקר; קליינט ההורדות {0} שם הורדות ב-{1} אבל הנתיב לא תקין {2}. בחן מחדש את ניתוב התיקיות והגדרות קליינט ההורדות.",
    "RemotePathMappingFolderPermissionsHealthCheckMessage": "ראדארר יכול לראות אבל לא לגשת לסרטים שירדו {0}. ככל הנראה בעיית הרשאות.",
    "RemotePathMappingHostHelpText": "אותו מארח שציינת עבור לקוח ההורדות המרוחק",
    "RemotePathMappingLocalPathHelpText": "נתיב שבו {appName} אמור להשתמש כדי לגשת לנתיב המרוחק באופן מקומי",
    "RemoveFailedDownloadsHelpText": "הסר הורדות שנכשלו מהיסטוריית הלקוחות להורדה",
    "RemoveFilter": "הסר את המסנן",
    "RemoveFromBlocklist": "הסר מהרשימה השחורה",
    "RemoveSelectedItemQueueMessageText": "האם אתה בטוח שברצונך להסיר את {0} פריט {1} מהתור?",
    "RemoveSelectedItemsQueueMessageText": "האם אתה בטוח שברצונך להסיר את {0} פריט {1} מהתור?",
    "RemovedFromTaskQueue": "הוסר מתור המשימות",
    "RemovingTag": "הסרת התג",
    "RenameEpisodesHelpText": "{appName} ישתמש בשם הקובץ הקיים אם שינוי שם אינו זמין",
    "Renamed": "שונה שם",
    "RescanSiteFolderAfterRefresh": "סרוק מחדש את תיקיית הסרט לאחר רענון",
    "Reset": "אִתחוּל",
    "Restart": "אתחול",
    "RestartLater": "אתחיל מאוחר יותר",
    "RestartRequiredHelpTextWarning": "נדרש הפעלה מחדש כדי להיכנס לתוקף",
    "RestartNow": "אתחל עכשיו",
    "RestartReloadNote": "הערה: {appName} יופעל מחדש אוטומטית וטען מחדש את ממשק המשתמש במהלך תהליך השחזור.",
    "Restore": "לשחזר",
    "RestoreBackup": "שחזור גיבוי",
    "RestrictionsLoadError": "לא ניתן לטעון את ההגבלות",
    "Result": "תוֹצָאָה",
    "Retention": "הַחזָקָה",
    "RetentionHelpText": "Usenet בלבד: הגדר לאפס כדי להגדיר לשימור בלתי מוגבל",
    "RootFolder": "תיקיית שורש",
    "RootFolderLoadError": "לא ניתן לטעון תיקיות שורש",
    "RootFolderMissingHealthCheckMessage": "תיקיית שורש חסרה: {0}",
    "RootFolders": "תיקיות שורש",
    "RootFoldersLoadError": "לא ניתן לטעון תיקיות שורש",
    "RssIsNotSupportedWithThisIndexer": "RSS אינו נתמך עם אינדקס זה",
    "RssSync": "סנכרון RSS",
    "Save": "להציל",
    "SaveChanges": "שמור שינויים",
    "SaveSettings": "שמור הגדרות",
    "ScriptPath": "נתיב סקריפט",
    "SearchByTpdbId": "אתה יכול גם לחפש באמצעות מזהה TMDb של סרט. למשל: 'tmdb: 71663'",
    "Search": "לחפש",
    "SearchAll": "חפש הכל",
    "SearchFailedError": "החיפוש נכשל. נסה שוב מאוחר יותר.",
    "SearchIsNotSupportedWithThisIndexer": "אינדקס זה אינו נתמך בחיפוש",
    "SearchSelected": "חיפוש נבחר",
    "Security": "בִּטָחוֹן",
    "Seeders": "זריעים",
    "SetPermissions": "הגדר הרשאות",
    "SetTags": "הגדר תגים",
    "Settings": "הגדרות",
    "ShortDateFormat": "פורמט תאריך קצר",
    "ShowAdvanced": "הצג מתקדם",
    "ShowQualityProfile": "הראה פרופיל איכות",
    "ShowQualityProfileHelpText": "הצג פרופיל איכות תחת פוסטר",
    "ShowRelativeDates": "הצג תאריכים יחסית",
    "ShowTitleHelpText": "הראה את שם הסרט תחת הכרזה",
    "ShowUnknownSiteItems": "הצג פריטי סרט לא ידועים",
    "ShowUnknownSiteItemsHelpText": "הצג פריטים ללא סרט בתור. זה יכול לכלול סרטים שהוסרו או כל דבר אחר בקטגוריה של {appName}",
    "Size": "גודל",
    "SizeOnDisk": "גודל בדיסק",
    "SkipFreeSpaceCheck": "דלג על בדיקת מקום פנוי",
    "SkipFreeSpaceCheckWhenImportingHelpText": "השתמש כאשר {appName} אינו מצליח לזהות מקום פנוי מתיקיית שורש הסרט שלך",
    "Socks4": "גרביים 4",
    "Socks5": "Socks5 (תמיכה ב- TOR)",
    "SomeResultsAreHiddenByTheAppliedFilter": "חלק מהתוצאות מוסתרות על ידי המסנן שהוחל",
    "Source": "מָקוֹר",
    "SourcePath": "נתיב מקור",
    "SourceRelativePath": "נתיב יחסי מקור",
    "StartupDirectory": "ספריית ההפעלה",
    "Status": "סטָטוּס",
    "Style": "סִגְנוֹן",
    "Sunday": "יוֹם רִאשׁוֹן",
    "SupportedCustomConditions": "{appName} תומך בתנאים מותאמים אישית כנגד מאפייני השחרור שלמטה.",
    "SupportedDownloadClients": "{appName} תומך בכל לקוח הורדות המשתמש בתקן Newznab, כמו גם בלקוחות הורדה אחרים המפורטים להלן.",
    "SupportedDownloadClientsMoreInfo": "למידע נוסף על לקוחות הורדה בודדים, לחץ על כפתורי המידע.",
    "SupportedImportListsMoreInfo": "למידע נוסף על רשימות הייבוא הבודדות, לחץ על כפתורי המידע.",
    "SupportedIndexersMoreInfo": "למידע נוסף על האינדקסים הבודדים, לחץ על כפתורי המידע.",
    "SupportedListsMoreInfo": "למידע נוסף על רשימות הייבוא הבודדות, לחץ על כפתורי המידע.",
    "System": "מערכת",
    "SystemTimeHealthCheckMessage": "זמן המערכת אינו פעיל יותר מיום אחד. משימות מתוזמנות עשויות שלא לפעול כראוי עד לתיקון הזמן",
    "TablePageSize": "גודל עמוד",
    "TablePageSizeHelpText": "מספר הפריטים להצגה בכל עמוד",
    "TagCannotBeDeletedWhileInUse": "לא ניתן למחוק בזמן השימוש",
    "TagIsNotUsedAndCanBeDeleted": "לא משתמשים בתג וניתן למחוק אותו",
    "Test": "מִבְחָן",
    "TestAllIndexers": "בדוק את כל האינדקסים",
    "TestAllLists": "בדוק את כל הרשימות",
    "Theme": "ערכת נושא",
    "Time": "זְמַן",
    "TimeFormat": "פורמט זמן",
    "TimeLeft": "הזמן שנותר",
    "Title": "כותרת",
    "Titles": "כותרות",
    "Today": "היום",
    "TorrentDelay": "עיכוב סיקור",
    "TorrentDelayHelpText": "התעכב תוך דקות להמתין לפני שתופס סיקור",
    "Torrents": "טורנטים",
    "TorrentsDisabled": "טורנטים מושבתים",
    "TotalFileSize": "גודל קובץ כולל",
    "TotalSpace": "השטח הכולל",
    "TpdbIdExcludeHelpText": "מזהה ה- TMDb של הסרט לא לכלול",
    "Trace": "זֵכֶר",
    "UiSettings": "הגדרות ממשק המשתמש",
    "UiSettingsSummary": "אפשרויות לקויות לוח שנה, תאריך וצבע",
    "UpdateSelected": "עדכון נבחר",
    "UpdateUiNotWritableHealthCheckMessage": "לא ניתן להתקין את העדכון מכיוון שתיקיית ממשק המשתמש '{0}' אינה ניתנת לכתיבה על ידי המשתמש '{1}'.",
    "UpgradeUntilCustomFormatScoreHelpText": "לאחר שהציון בפורמט מותאם אישית זה יגיע, {appName} כבר לא יוריד סרטים",
    "WaitingToImport": "ממתין לייבוא",
    "WaitingToProcess": "מחכה לעיבוד",
    "WhyCantIFindMySite": "למה אני לא יכול למצוא את הסרט שלי?",
    "Wiki": "וויקי",
    "Yes": "כן",
    "AppDataDirectory": "ספריית AppData",
    "BackupNow": "גיבוי עכשיו",
    "Languages": "שפות",
    "Remove": "לְהַסִיר",
    "SelectAll": "בחר הכל",
    "SelectDropdown": "'בחר...",
    "SetPermissionsLinuxHelpText": "האם להפעיל את chmod כאשר מייבאים / משנים קבצים?",
    "SelectFolder": "בחר תיקייה",
    "SelectLanguage": "בחר שפה",
    "SendAnonymousUsageData": "שלח נתוני שימוש אנונימיים",
    "SetPermissionsLinuxHelpTextWarning": "אם אינך בטוח מה הגדרות אלה עושות, אל תשנה אותן.",
    "ShowDateAdded": "הצגת תאריך הוספה",
    "ShowMonitored": "הצג פיקוח",
    "ShowMonitoredHelpText": "הצג סטטוס פיקוח תחת פוסטר",
    "ShowSearch": "הצג חיפוש",
    "ShowSearchHelpText": "הצג את לחצן החיפוש ברחף",
    "ShowPath": "הצג נתיב",
    "ShowRelativeDatesHelpText": "הצג תאריכים קרובים (היום / אתמול / וכו ') או תאריכים מוחלטים",
    "ShowSizeOnDisk": "הצג גודל בדיסק",
    "Shutdown": "לכבות",
    "SiteCannotBeFound": "מצטערים, הסרט הזה לא נמצא.",
    "SslCertPassword": "סיסמת אישורי SSL",
    "SslCertPath": "נתיב אישורי SSL",
    "SslCertPathHelpText": "נתיב לקובץ pfx",
    "SslPort": "יציאת SSL",
    "UnselectAll": "בטל את הבחירה בכול",
    "Warn": "לְהַזהִיר",
    "Week": "שָׁבוּעַ",
    "WeekColumnHeader": "כותרת עמודות שבוע",
    "Wanted": "מבוקש",
    "AddAutoTagError": "לא ניתן להוסיף רשימה חדשה, אנא נסה שוב.",
    "AddConditionError": "לא ניתן להוסיף תנאי חדש, נסה שוב.",
    "AddCustomFormat": "הוסף פורמט מותאם אישית",
    "AddCustomFormatError": "לא ניתן להוסיף פורמט מותאם אישית חדש, נסה שוב.",
    "AddDelayProfile": "הוסף פרופיל עיכוב",
    "AddImportListExclusion": "מחק אי הכללת רשימות ייבוא",
    "AddIndexerError": "לא ניתן להוסיף אינדקס חדש, נסה שוב.",
    "AddImportListExclusionError": "לא ניתן להוסיף אי הכללה ברשימה חדשה, נסה שוב.",
    "AddIndexer": "הוסף אינדקס",
    "AddList": "הוסף רשימה",
    "AddListError": "לא ניתן להוסיף רשימה חדשה, אנא נסה שוב.",
    "AddRemotePathMapping": "הוסף מיפוי נתיבים מרוחק",
    "AddNotificationError": "לא ניתן להוסיף התראה חדשה, נסה שוב.",
    "AddQualityProfile": "הוסף פרופיל איכות",
    "AddQualityProfileError": "לא ניתן להוסיף פרופיל איכות חדש, נסה שוב.",
    "AddRemotePathMappingError": "לא ניתן להוסיף מיפוי נתיבים מרוחק חדש, נסה שוב.",
    "AfterManualRefresh": "לאחר רענון ידני",
    "BrowserReloadRequired": "חובה לטעון דפדפן",
    "BypassDelayIfHighestQuality": "עקוף במידה והאיכות גבוהה יותר",
    "DeleteSelectedIndexers": "מחק את אינדקס",
    "DoneEditingGroups": "עריכת קבוצות הסתיימה",
    "DotNetVersion": ".NET Core",
    "ExtraFileExtensionsHelpTextsExamples": "דוגמאות: '.sub, .nfo' או 'sub, nfo'",
    "Indexers": "אינדקסים",
    "Logs": "יומנים",
    "MediaManagement": "ניהול מדיה",
    "NoMatchFound": "לא נמצאה התאמה!",
    "QualityProfile": "פרופיל איכות",
    "RemotePathMappings": "מיפוי נתיבים מרוחק",
    "AlreadyInYourLibrary": "כבר בספרייה שלך",
    "AgeWhenGrabbed": "גיל (כאשר תופס)",
    "Always": "תמיד",
    "Agenda": "סֵדֶר הַיוֹם",
    "AnalyseVideoFiles": "ניתוח קבצי וידאו",
    "AppDataLocationHealthCheckMessage": "לא ניתן יהיה לעדכן את מחיקת AppData בעדכון",
    "ApplyTags": "החל תגים",
    "ApplyTagsHelpTextAdd": "הוסף: הוסף את התגים לרשימת התגים הקיימת",
    "ApplyTagsHelpTextHowToApplyDownloadClients": "כיצד להחיל תגים על הסרטים שנבחרו",
    "ApplyTagsHelpTextHowToApplyImportLists": "כיצד להחיל תגים על הסרטים שנבחרו",
    "ApplyTagsHelpTextHowToApplyIndexers": "כיצד להחיל תגים על הסרטים שנבחרו",
    "ApplyTagsHelpTextHowToApplySeries": "כיצד להחיל תגים על הסרטים שנבחרו",
    "ApplyTagsHelpTextRemove": "הסר: הסר את התגים שהוזנו",
    "AptUpdater": "השתמש ב- apt כדי להתקין את העדכון",
    "ChownGroupHelpTextWarning": "זה עובד רק אם המשתמש שמפעיל את {appName} הוא הבעלים של הקובץ. עדיף להבטיח שלקוח ההורדה ישתמש באותה קבוצה כמו {appName}.",
    "Clear": "ברור",
    "ClientPriority": "עדיפות לקוח",
    "CloneCustomFormat": "תבנית מותאמת אישית של שיבוט",
    "CloneIndexer": "אינדקס שיבוט",
    "CloneProfile": "פרופיל שיבוט",
    "Close": "סגור",
    "ColonReplacement": "החלפת המעי הגס",
    "CompletedDownloadHandling": "הטיפול בהורדות הושלם",
    "Component": "רְכִיב",
    "ColonReplacementFormatHelpText": "שנה את האופן שבו {appName} מטפל בהחלפת המעי הגס",
    "Condition": "תנאים",
    "ConditionUsingRegularExpressions": "תנאי זה תואם שימוש בביטויים רגולריים. שים לב שלדמויות {0} יש משמעויות מיוחדות וצריך לברוח באמצעות {1}",
    "Conditions": "תנאים",
    "Connect": "לְחַבֵּר",
    "ConnectSettings": "חבר הגדרות",
    "Connections": "חיבורים",
    "CopyToClipboard": "העתק ללוח",
    "CopyUsingHardlinksHelpTextWarning": "לעיתים, נעילת קבצים עשויה למנוע שינוי שם של קבצים שנזרעים. אתה יכול להשבית זמנית את הזריעה ולהשתמש בפונקציית השם של {appName} כעבודה מסביב.",
    "CouldNotFindResults": "לא נמצאו תוצאות עבור '{0}'",
    "CustomFormatHelpText": "{appName} קולע כל מהדורה באמצעות סכום הציונים לתבניות מותאמות אישית. אם מהדורה חדשה תשפר את הציון, באותה איכות או טובה יותר, רדאר יתפוס אותה.",
    "CreateEmptySiteFoldersHelpText": "צור תיקיות סרט חסרות במהלך סריקת הדיסק",
    "CreateGroup": "צור קבוצה",
    "CurrentlyInstalled": "מותקן כעת",
    "Custom": "המותאם אישית",
    "DeleteImportListExclusion": "מחק אי הכללת רשימות ייבוא",
    "DeleteEmptyFolders": "מחק תיקיות ריקות",
    "DeleteEmptyFoldersHelpText": "מחק תיקיות סרטים ריקות במהלך סריקת הדיסק וכאשר קבצי סרט נמחקים",
    "DoNotPrefer": "לא מעדיפים",
    "DoNotUpgradeAutomatically": "אל תשדרג אוטומטית",
    "Docker": "דוקר",
    "DockerUpdater": "עדכן את מיכל העגינה לקבל את העדכון",
    "Donations": "תרומות",
    "Download": "הורד",
    "DownloadClient": "הורד לקוח",
    "EditListExclusion": "ערוך אי הכללת רשימה",
    "GeneralSettingsLoadError": "לא ניתן לטעון את ההגדרות הכלליות",
    "GeneralSettingsSummary": "יציאה, SSL, שם משתמש / סיסמה, פרוקסי, ניתוחים ועדכונים",
    "Global": "גלוֹבָּלִי",
    "Ignored": "התעלמו",
    "IgnoredAddresses": "כתובות שהתעלמו מהן",
    "Images": "תמונות",
    "Import": "יְבוּא",
    "ImportCustomFormat": "ייבא פורמט מותאם אישית",
    "ImportErrors": "ייבוא שגיאות",
    "ImportExistingSites": "ייבא סרטים קיימים",
    "ImportExtraFiles": "ייבא קבצים נוספים",
    "ImportExtraFilesHelpText": "ייבא קבצים נוספים תואמים (כתוביות, nfo וכו ') לאחר ייבוא קובץ סרט",
    "ImportListExclusions": "מחק אי הכללת רשימות ייבוא",
    "IncludeUnmonitored": "כלול ללא פיקוח",
    "IndexerDownloadClientHelpText": "ציין איזה קליינט הורדה משתמש באינדקסר הזה להורדה",
    "IndexerOptionsLoadError": "לא ניתן לטעון אפשרויות לאינדקס",
    "IndexerPriority": "עדיפות אינדקס",
    "IndexerRssNoIndexersAvailableHealthCheckMessage": "כל האינדקסים התומכים ב- rss אינם זמינים באופן זמני בגלל שגיאות אינדקס האחרונות",
    "IndexerRssNoIndexersEnabledHealthCheckMessage": "אין אינדקסים זמינים כאשר סינכרון RSS מופעל, Radarr לא תפס אוטומטית גרסאות חדשות",
    "IndexerSearchNoAutomaticHealthCheckMessage": "אין אינדקסים זמינים כאשר חיפוש אוטומטי מופעל, Radarr לא תספק תוצאות חיפוש אוטומטיות",
    "IndexerSearchNoAvailableIndexersHealthCheckMessage": "כל האינדקסים הניתנים לחיפוש אינם זמינים באופן זמני בגלל שגיאות אינדקס האחרונות",
    "ListExclusionsLoadError": "לא ניתן לטעון אי הכללות ברשימה",
    "ListOptionsLoadError": "לא ניתן לטעון אפשרויות רשימה",
    "MaximumSizeHelpText": "גודל מרבי לתפיסה שניתן יהיה לתפוס ב- MB. הגדר לאפס כדי להגדיר ללא הגבלה",
    "Mechanism": "מַנגָנוֹן",
    "MediaInfo": "מידע מדיה",
    "MonitorNone": "אף אחד",
    "NextExecution": "הביצוע הבא",
    "NoBackupsAreAvailable": "אין גיבויים",
    "NoChange": "ללא שינוי",
    "NoChanges": "אין שינויים",
    "OnLatestVersion": "הגרסה האחרונה של {appName} כבר מותקנת",
    "OnRename": "על שינוי שם",
    "OnUpgrade": "בשדרוג",
    "OnlyUsenet": "רק Usenet",
    "OpenBrowserOnStart": "פתח את הדפדפן בהתחלה",
    "Options": "אפשרויות",
    "OpenBrowserOnStartHelpText": " פתח דפדפן אינטרנט ונווט אל דף הבית של {appName} בהתחלת האפליקציה.",
    "ProcessingFolders": "תיקיות עיבוד",
    "Profiles": "פרופילים",
    "QueueLoadError": "טעינת התור נכשלה",
    "Rating": "דירוגים",
    "ReadTheWikiForMoreInformation": "קרא את הוויקי למידע נוסף",
    "Real": "אמיתי",
    "Reason": "סיבה",
    "RecyclingBin": "סל מיחזור",
    "RecyclingBinCleanup": "ניקוי סל המיחזור",
    "RecyclingBinCleanupHelpText": "הגדר ל 0 כדי להשבית ניקוי אוטומטי",
    "RecyclingBinCleanupHelpTextWarning": "קבצים בסל המיחזור ישנים יותר ממספר הימים שנבחר ינוקו באופן אוטומטי",
    "RemoveFromDownloadClient": "הסר מלקוח ההורדות",
    "RemoveFromDownloadClientHelpTextWarning": "הסרה תסיר את ההורדה ואת הקבצים מלקוח ההורדה.",
    "RemoveFromQueue": "הסר מהתור",
    "RemoveQueueItemConfirmation": "האם אתה בטוח שברצונך להסיר את {0} פריט {1} מהתור?",
    "RemoveRootFolder": "הסר את תיקיית השורש",
    "RemoveSelected": "הסר פריטים שנבחרו",
    "RemoveSelectedBlocklistMessageText": "האם אתה בטוח שברצונך להסיר את הפריטים שנבחרו מהרשימה השחורה?",
    "ResetAPIKey": "אפס את מפתח ה- API",
    "ResetAPIKeyMessageText": "האם אתה בטוח שברצונך לאפס את מפתח ה- API שלך?",
    "RssSyncIntervalHelpText": "מרווח בדקות. הגדר לאפס כדי להשבית (זה יפסיק את כל תפיסת השחרור האוטומטית)",
    "RssSyncIntervalHelpTextWarning": "זה יחול על כל האינדקסים, אנא עקוב אחר הכללים שנקבעו על ידם",
    "Runtime": "זמן ריצה",
    "RssSyncInterval": "מרווח סינכרון RSS",
    "SitesLoadError": "לא ניתן לטעון רשימות",
    "Unmonitored": "ללא פיקוח",
    "UnmonitorDeletedEpisodesHelpText": "סרטים שנמחקו מהדיסק אינם מנוטרים אוטומטית ב- {appName}",
    "RemotePathMappingRemotePathHelpText": "נתיב שורש לספריה אליה ניגש לקוח ההורדה",
    "RemotePathMappingWrongOSPathHealthCheckMessage": "אתה משתמש בדוקר; קליינט ההורדות {0} שם הורדות ב-{1} אבל הנתיב לא תקין {2}. בחן מחדש את ניתוב התיקיות והגדרות קליינט ההורדות.",
    "RescanAfterRefreshHelpTextWarning": "{appName} לא יאתר אוטומטית שינויים בקבצים כאשר לא מוגדר כ'תמיד '",
    "Reorder": "להזמין מחדש",
    "ShownClickToHide": "מוצג, לחץ כדי להסתיר",
    "RecyclingBinHelpText": "קבצי סרט יעלו לכאן כאשר יימחקו במקום שיימחקו לצמיתות",
    "ReleaseGroup": "קבוצת שחרור",
    "IncludeCustomFormatWhenRenamingHelpText": "כלול בתבנית שינוי שם של {פורמטים מותאמים אישית}",
    "No": "לא",
    "PendingChangesDiscardChanges": "מחק שינויים ועזוב",
    "Replace": "החלף",
    "ReplaceIllegalCharacters": "החלף תווים לא חוקיים",
    "IndexerSettings": "הגדרות אינדקס",
    "IndexerStatusAllUnavailableHealthCheckMessage": "כל האינדקסים אינם זמינים עקב כשלים",
    "IndexerStatusUnavailableHealthCheckMessage": "אינדקסים לא זמינים בגלל כשלים: {0}",
    "IndexerTagHelpText": "השתמש באינדקסר זה רק לסרטים שתואמים לתויות. השאר ריק כדי לחפש את כל הסרטים.",
    "MetadataLoadError": "לא ניתן לטעון מטא נתונים",
    "Scheduled": "מתוזמן",
    "Score": "ציון",
    "ReplaceIllegalCharactersHelpText": "החלף תווים לא חוקיים. אם לא מסומן, {appName} יסיר אותם במקום זאת",
    "AddListExclusion": "הוסף אי הכללת רשימה",
    "AddNewSiteRootFolderHelpText": "תיקיית המשנה '{0}' תיווצר באופן אוטומטי",
    "AutoRedownloadFailedHelpText": "חפש אוטומטית ונסה להוריד מהדורה אחרת",
    "DeleteQualityProfileMessageText": "האם אתה בטוח שברצונך למחוק את פרופיל האיכות {0}",
    "DeleteReleaseProfile": "מחק פרופיל עיכוב",
    "DeleteReleaseProfileMessageText": "האם אתה בטוח שברצונך למחוק את פרופיל האיכות {0}",
    "DeleteRemotePathMapping": "ערוך מיפוי נתיבים מרחוק",
    "DeleteSiteFolderConfirmation": "תיקיית הסרטים '{0}' וכל תוכן זה יימחקו.",
    "DeleteSiteFolderHelpText": "מחק את תיקיית הסרט ואת תוכנו",
    "DeleteSpecification": "מחק הודעה",
    "EnableCompletedDownloadHandlingHelpText": "ייבא אוטומטית הורדות שהושלמו מלקוח ההורדות",
    "EnableInteractiveSearch": "אפשר חיפוש אינטראקטיבי",
    "EnableInteractiveSearchHelpText": "ישמש כאשר נעשה שימוש בחיפוש אינטראקטיבי",
    "EnableMetadataHelpText": "אפשר יצירת קובץ מטא-נתונים עבור סוג מטא-נתונים זה",
    "Here": "כאן",
    "HiddenClickToShow": "מוסתר, לחץ להצגה",
    "RemotePathMappingsLoadError": "לא ניתן לטעון מיפוי נתיבים מרוחק",
    "RenameFiles": "שנה את שם הקבצים",
    "Analytics": "ניתוח",
    "AuthenticationRequiredHelpText": "הגדר עבור אילו קריאות נדרש אימות. עדיף להשאיר את ברירת המחדל.",
    "DeleteNotificationMessageText": "האם אתה בטוח שברצונך למחוק את פרופיל האיכות {0}",
    "EnableColorImpairedModeHelpText": "סגנון שונה כדי לאפשר למשתמשים לקויי צבע להבחין טוב יותר במידע המקודד בצבע",
    "AddCustomFilter": "הוספת פילטר מותאם",
    "AnalyticsEnabledHelpText": "שלח פרטי שימוש ושגיאה אנונימיים לשרתי {appName}. זה כולל מידע בדפדפן שלך, אילו דפי {appName} WebUI אתה משתמש, דיווח על שגיאות וכן מערכת הפעלה וגרסת זמן ריצה. אנו נשתמש במידע זה כדי לתעדף תכונות ותיקוני באגים.",
    "BlocklistLoadError": "לא ניתן לטעון את הרשימה השחורה",
    "ICalShowAsAllDayEvents": "הראה כאירועי כל היום",
    "DownloadClientCheckUnableToCommunicateWithHealthCheckMessage": "לא ניתן לתקשר עם {0}.",
    "DownloadClientOptionsLoadError": "לא ניתן לטעון אפשרויות לקוח להורדה",
    "QualitiesLoadError": "לא ניתן לטעון איכויות",
    "SupportedIndexers": "{appName} תומך בכל אינדקס שמשתמש בתקן Newznab, כמו גם באינדקסים אחרים המפורטים להלן.",
    "AddDownloadClient": "הוסף לקוח הורדות",
    "AddDownloadClientError": "לא ניתן להוסיף לקוח הורדות חדש, נסה שוב.",
    "AddExclusion": "הוסף אי הכללה",
    "AllResultsAreHiddenByTheAppliedFilter": "כל התוצאות מוסתרות על ידי המסנן שהוחל",
    "ApplyTagsHelpTextReplace": "החלף: החלף את התגים בתגיות שהוזנו (אין להזין תגים כדי למחוק את כל התגים)",
    "AuthBasic": "בסיסי (חלון קופץ לדפדפן)",
    "AuthForm": "טפסים (דף כניסה)",
    "Authentication": "אימות",
    "AuthenticationRequired": "נדרש אימות",
    "AuthenticationMethodHelpText": "דרוש שם משתמש וסיסמה כדי לגשת ל {appName}",
    "ConnectSettingsSummary": "התראות, חיבורים לשרתי מדיה / נגנים ותסריטים מותאמים אישית",
    "CustomFormat": "פורמט מותאם אישית",
    "IndexerPriorityHelpText": "עדיפות אינדקס מ -1 (הגבוה ביותר) ל -50 (הנמוך ביותר). ברירת מחדל: 25.",
    "AuthenticationRequiredWarning": "בכדי למנוע גישה מרחוק ללא אימות, {appName} דורש הגדרת אימות.\nהגדר את הפרטים ושיטת האימות. ישנה אפשרות לדלג על אימות מהרשת הביתית שלך. \nבמידת הצורך יש לפנות אל שו״ת למידע נוסף.",
    "BackupRetentionHelpText": "גיבויים אוטומטיים ישנים יותר מתקופת השמירה ינוקו אוטומטית",
    "BlocklistRelease": "שחרור הרשימה השחורה",
    "BuiltIn": "נִבנָה בְּ",
    "Cancel": "לְבַטֵל",
    "DelayProfile": "עיכוב פרופיל",
    "DeleteAutoTagHelpText": "האם אתה בטוח שברצונך למחוק את פרופיל האיכות {0}",
    "DeleteBackup": "מחק את הגיבוי",
    "DeleteImportListMessageText": "האם אתה בטוח שברצונך למחוק את פרופיל האיכות {0}",
    "Discord": "דיסקורד",
    "DiskSpace": "שטח דיסק",
    "DownloadClientRootFolderHealthCheckMessage": "הורד לקוח {0} ממקם הורדות בתיקיית הבסיס {1}. אתה לא צריך להוריד לתיקיית שורש.",
    "DownloadClientStatusAllClientHealthCheckMessage": "כל לקוחות ההורדה אינם זמינים עקב כשלים",
    "DownloadClientStatusSingleClientHealthCheckMessage": "הורדת לקוחות לא זמינה עקב כשלים: {0}",
    "DownloadClientTagHelpText": "השתמש באינדקסר זה רק לסרטים שתואמים לתויות. השאר ריק כדי לחפש את כל הסרטים.",
    "ExternalUpdater": "{appName} מוגדר להשתמש במנגנון עדכון חיצוני",
    "Group": "קְבוּצָה",
    "HardlinkCopyFiles": "קישור קשיח / העתק קבצים",
    "IncludeHealthWarnings": "כלול אזהרות בריאות",
    "IndexerLongTermStatusUnavailableHealthCheckMessage": "אינדקסים לא זמינים עקב כשלים במשך יותר משש שעות: {0}",
    "Info": "מידע",
    "InstallLatest": "התקן את האחרונה",
    "InvalidFormat": "פורמט לא חוקי",
    "KeyboardShortcutsOpenModal": "פתח את המודאל הזה",
    "KeyboardShortcutsSaveSettings": "שמור הגדרות",
    "LibraryImportTipsDontUseDownloadsFolder": "אל תשתמש לייבוא הורדות מלקוח ההורדות שלך, זה נועד רק לספריות מאורגנות קיימות, ולא לקבצים שאינם ממוינים.",
    "ManualImportItemsLoadError": "לא ניתן לטעון פריטי ייבוא ידניים",
    "Max": "מקסימום",
    "MinimumAgeHelpText": "Usenet בלבד: גיל מינימלי בדקות של NZB לפני שהם נתפסים. השתמש בזה כדי לתת למהדורות חדשות זמן להפצה לספק ה- usenet שלך.",
    "MinimumCustomFormatScore": "ציון פורמט מותאם אישית מינימלי",
    "MinimumCustomFormatScoreHelpText": "ציון פורמט מותאם אישית מינימלי מורשה להורדה",
    "NoSitesHaveBeenAdded": "עדיין לא הוספת סרטים, האם ברצונך לייבא חלק מהסרטים או את כולם קודם?",
    "NotificationsLoadError": "לא ניתן לטעון התראות",
    "OrganizeNothingToRename": "הַצלָחָה! העבודה שלי נעשית, אין קבצים לשינוי שם.",
    "OriginalLanguage": "שפת מקור",
    "OutputPath": "נתיב פלט",
    "Posters": "כרזות",
    "PreferAndUpgrade": "העדפה ושדרג",
    "PreferTorrent": "העדיפו את טורנט",
    "PreferUsenet": "העדיפו את Usenet",
    "PreferredProtocol": "פרוטוקול מועדף",
    "PreferredSize": "גודל מועדף",
    "Proper": "תָקִין",
    "ProtocolHelpText": "בחר באיזה פרוטוקול (ים) להשתמש ואיזה מהם עדיף בעת בחירה בין מהדורות שוות אחרת",
    "Quality": "איכות",
    "QueueIsEmpty": "התור ריק",
    "RemotePathMappingDownloadPermissionsHealthCheckMessage": "ראדארר יכול לראות אבל לא לגשת לסרטים שירדו {0}. ככל הנראה בעיית הרשאות.",
    "ReplaceWithDash": "החלף ב- Dash",
    "ReplaceWithSpaceDash": "החלף במקף החלל",
    "ReplaceWithSpaceDashSpace": "החלף במרחב מקף החלל",
    "Required": "נדרש",
    "RescanAfterRefreshHelpText": "סרוק מחדש את תיקיית הסרט לאחר רענון הסרט",
    "Script": "תַסרִיט",
    "SearchForMissing": "חפש חסר",
    "UiLanguageHelpText": "שפה בה {appName} ישתמש עבור ממשק המשתמש",
    "UiSettingsLoadError": "לא ניתן לטעון הגדרות ממשק משתמש",
    "UnsavedChanges": "שינויים שלא נשמרו",
    "UpdateAutomaticallyHelpText": "הורד והתקין עדכונים באופן אוטומטי. עדיין תוכל להתקין ממערכת: עדכונים",
    "UpdateMechanismHelpText": "השתמש במעדכן המובנה של {appName} או בסקריפט",
    "UpdateWhisparrDirectlyLoadError": "לא ניתן לעדכן את {appName} ישירות,",
    "UpdateScriptPathHelpText": "נתיב לסקריפט מותאם אישית שלוקח חבילת עדכון שחולצה ומטפל בשארית תהליך העדכון",
    "UpdateStartupNotWritableHealthCheckMessage": "לא ניתן להתקין את העדכון מכיוון שתיקיית ההפעלה '{0}' אינה ניתנת לכתיבה על ידי המשתמש '{1}'.",
    "UpdateStartupTranslocationHealthCheckMessage": "לא ניתן להתקין את העדכון מכיוון שתיקיית ההפעלה '{0}' נמצאת בתיקיית טרנסלוקציה של אפליקציות.",
    "UpdateUINotWritableHealthCheckMessage": "לא ניתן להתקין את העדכון מכיוון שתיקיית ממשק המשתמש '{0}' אינה ניתנת לכתיבה על ידי המשתמש '{1}'.",
    "UpgradeUntilCustomFormatScore": "שדרג עד ציון פורמט מותאם אישית",
    "UpgradeUntilHelpText": "לאחר שהאיכות הזו תושג {appName} כבר לא תוריד סרטים",
    "UpgradeUntilThisQualityIsMetOrExceeded": "שדרג עד שתתקיים או תחרוג מאיכות זו",
    "Usenet": "Usenet",
    "UsenetDelay": "עיכוב Usenet",
    "UsenetDelayHelpText": "עיכוב תוך דקות להמתין לפני שתופס שחרור מאוסנט",
    "Username": "שם משתמש",
    "Version": "גִרְסָה",
    "VideoCodec": "Codec וידאו",
    "View": "נוף",
    "VisitTheWikiForMoreDetails": "בקר בוויקי לפרטים נוספים: ",
    "WeekColumnHeaderHelpText": "מוצג מעל כל עמודה כאשר השבוע היא התצוגה הפעילה",
    "WhatsNew": "מה חדש?",
    "Year": "שָׁנָה",
    "SiteIsMonitored": "הסרט אינו מנוטר",
    "DeleteDownloadClientMessageText": "האם אתה בטוח שברצונך למחוק את פרופיל האיכות {0}",
    "FailedToLoadUiSettingsFromApi": "טעינת הסרט נכשלה מה- API נכשלה",
    "RetryingDownloadOn": "מעכב את ההורדה עד {0} בשעה {1}",
    "FormatAgeHour": "שעה (ות",
    "AutoTaggingNegateHelpText": "אם מסומן, הפורמט המותאם אישית לא יחול אם תנאי זה {0} תואם.",
    "DeleteSiteFolders": "מחק תיקיות ריקות",
    "DeleteSiteFoldersHelpText": "מחק את תיקיית הסרט ואת תוכנו"
}
