{
    "Language": "Ngôn ngữ",
    "HiddenClickToShow": "Ẩn, bấm để hiển thị",
    "ShownClickToHide": "Hiển thị, nhấp để ẩn",
    "HideAdvanced": "Ẩn nâng cao",
    "ShowAdvanced": "Hiển thị nâng cao",
    "AppDataDirectory": "Thư mục AppData",
    "Calendar": "Lịch",
    "Cancel": "Huỷ bỏ",
    "DeleteCustomFormat": "Xóa định dạng tùy chỉnh",
    "DeleteSelectedDownloadClients": "Xóa ứng dụng khách tải xuống",
    "Donations": "Quyên góp",
    "ExistingTag": "Thẻ hiện có",
    "Ignored": "Mặc kệ",
    "Indexers": "Người lập chỉ mục",
    "NoEventsFound": "Không tìm thấy sự kiện",
    "AddRemotePathMapping": "Thêm ánh xạ đường dẫn từ xa",
    "UiLanguage": "Ngôn ngữ giao diện người dùng",
    "UiLanguageHelpText": "Ngôn ngữ mà Lidarr sẽ sử dụng cho giao diện người dùng",
    "Age": "Tuổi tác",
    "All": "Tất cả",
    "ApplyTagsHelpTextHowToApplyDownloadClients": "Cách áp dụng thẻ cho các phim đã chọn",
    "ApplyTagsHelpTextHowToApplyImportLists": "Cách áp dụng thẻ cho các phim đã chọn",
    "AudioInfo": "Thông tin âm thanh",
    "Backup": "Sao lưu",
    "BackupNow": "Sao lưu ngay",
    "Backups": "Sao lưu",
    "BeforeUpdate": "Trước khi cập nhật",
    "Blocklist": "Danh sách chặn",
    "BlocklistReleaseHelpText": "Ngăn chặn Radarr không lấy bản phát hành này nữa",
    "BlocklistReleases": "Phát hành danh sách đen",
    "CancelPendingTask": "Bạn có chắc chắn muốn hủy nhiệm vụ đang chờ xử lý này không?",
    "Certification": "Chứng chỉ",
    "Clear": "Thông thoáng",
    "CloneCustomFormat": "Định dạng tùy chỉnh sao chép",
    "Close": "Đóng",
    "Component": "Thành phần",
    "DeleteBackup": "Xóa bản sao lưu",
    "DeleteBackupMessageText": "Bạn có chắc chắn muốn xóa cấu hình chất lượng không {0}",
    "DeleteCustomFormatMessageText": "Bạn có chắc chắn muốn xóa thẻ '{0}' không?",
    "DeleteSelectedIndexers": "Xóa trình lập chỉ mục",
    "Deleted": "Đã xóa",
    "Docker": "Docker",
    "DockerUpdater": "cập nhật vùng chứa docker để nhận bản cập nhật",
    "DotNetVersion": ".NET Core",
    "UiSettings": "Cài đặt giao diện người dùng",
    "UiSettingsLoadError": "Không thể tải cài đặt giao diện người dùng",
    "UiSettingsSummary": "Lịch, ngày tháng và các tùy chọn bị suy giảm màu sắc",
    "UnableToLoadBackups": "Không thể tải các bản sao lưu",
    "Download": "Tải xuống",
    "DownloadClient": "Tải xuống ứng dụng khách",
    "DownloadClientCheckNoneAvailableHealthCheckMessage": "Không có ứng dụng khách tải xuống nào",
    "DownloadClientCheckUnableToCommunicateWithHealthCheckMessage": "Không thể giao tiếp với {0}.",
    "DownloadClientRootFolderHealthCheckMessage": "Tải xuống ứng dụng khách {0} đặt các bản tải xuống trong thư mục gốc {1}. Bạn không nên tải xuống thư mục gốc.",
    "DownloadClients": "Tải xuống ứng dụng khách",
    "DownloadClientStatusSingleClientHealthCheckMessage": "Ứng dụng khách tải xuống không khả dụng do lỗi: {0}",
    "Edit": "Biên tập",
    "EnableAutomaticSearch": "Bật tìm kiếm tự động",
    "Error": "lỗi",
    "ErrorRestoringBackup": "Lỗi khi khôi phục bản sao lưu",
    "EventType": "Loại sự kiện",
    "Exception": "ngoại lệ",
    "Activity": "Hoạt động",
    "Add": "Thêm vào",
    "AddingTag": "Thêm thẻ",
    "AddNew": "Thêm mới",
    "Apply": "Ứng dụng",
    "ApplyTags": "Áp dụng thẻ",
    "ApplyTagsHelpTextRemove": "Xóa: Xóa các thẻ đã nhập",
    "ApplyTagsHelpTextAdd": "Thêm: Thêm thẻ vào danh sách thẻ hiện có",
    "Connect": "Kết nối",
    "Health": "Sức khỏe",
    "History": "Lịch sử",
    "HomePage": "Trang chủ",
    "ImportListStatusUnavailableHealthCheckMessage": "Danh sách không có sẵn do lỗi: {0}",
    "Imported": "Đã nhập khẩu",
    "ImportListStatusAllUnavailableHealthCheckMessage": "Tất cả danh sách không có sẵn do lỗi",
    "IncludeUnmonitored": "Bao gồm Không theo dõi",
    "Indexer": "Người lập chỉ mục",
    "IndexerSearchNoInteractiveHealthCheckMessage": "Không có trình chỉ mục nào có sẵn khi bật Tìm kiếm tương tác, Lidarr sẽ không cung cấp bất kỳ kết quả tìm kiếm tương tác nào",
    "IndexerStatusAllUnavailableHealthCheckMessage": "Tất cả các trình lập chỉ mục không khả dụng do lỗi",
    "Info": "Thông tin",
    "Languages": "Ngôn ngữ",
    "LastDuration": "lastDuration",
    "Location": "Vị trí",
    "Manual": "Thủ công",
    "MediaManagement": "Quản lý truyền thông",
    "Message": "Thông điệp",
    "Metadata": "metadata",
    "Missing": "Còn thiếu",
    "NoUpdatesAreAvailable": "Không có bản cập nhật nào có sẵn",
    "OnLatestVersion": "Phiên bản mới nhất của Radarr đã được cài đặt",
    "Options": "Tùy chọn",
    "Path": "Con đường",
    "QualityProfile": "Hồ sơ chất lượng",
    "ProxyResolveIpHealthCheckMessage": "Không thể phân giải Địa chỉ IP cho Máy chủ Proxy đã Định cấu hình {0}",
    "Quality": "Chất lượng",
    "Queue": "Xếp hàng",
    "Queued": "Đã xếp hàng",
    "Rating": "Xếp hạng",
    "Real": "Thực tế",
    "RemoveFromDownloadClient": "Xóa khỏi ứng dụng khách tải xuống",
    "Renamed": "Đã đổi tên",
    "RemovingTag": "Xóa thẻ",
    "Settings": "Cài đặt",
    "Size": "Kích thước",
    "StartupDirectory": "Thư mục khởi động",
    "Status": "Trạng thái",
    "System": "Hệ thống",
    "Tags": "Thẻ",
    "Unmonitored": "Không giám sát",
    "UpdateStartupNotWritableHealthCheckMessage": "Không thể cài đặt bản cập nhật vì người dùng '{0}' không thể ghi thư mục khởi động '{1}'.",
    "Warn": "Cảnh báo",
    "AddAutoTagError": "Không thể thêm danh sách mới, vui lòng thử lại.",
    "DefaultCase": "Trường hợp mặc định",
    "DelayProfile": "Hồ sơ trì hoãn",
    "DelayProfileTagsHelpText": "Áp dụng cho phim có ít nhất một thẻ phù hợp",
    "DelayProfiles": "Hồ sơ trì hoãn",
    "ListOptionsLoadError": "Không thể tải các tùy chọn danh sách",
    "NoResultsFound": "không tìm thấy kết quả nào",
    "NoSitesHaveBeenAdded": "Bạn chưa thêm phim nào, trước tiên bạn có muốn nhập một số hay tất cả phim của mình không?",
    "None": "không ai",
    "NotificationTriggers": "Kích hoạt thông báo",
    "NotificationsLoadError": "Không thể tải thông báo",
    "Security": "Bảo vệ",
    "Seeders": "Máy gieo hạt",
    "SelectFolder": "Chọn thư mục",
    "SendAnonymousUsageData": "Gửi dữ liệu sử dụng ẩn danh",
    "SetPermissions": "Đặt quyền",
    "SetPermissionsLinuxHelpText": "Có nên chạy chmod khi tệp được nhập / đổi tên không?",
    "Added": "Đã thêm",
    "DeleteConditionMessageText": "Bạn có chắc chắn muốn xóa cấu hình chất lượng không {0}",
    "Date": "Ngày",
    "TimeFormat": "Định dạng thời gian",
    "TimeLeft": "Thời gian còn lại",
    "Title": "Tiêu đề",
    "TorrentDelay": "Torrent Delay",
    "TorrentDelayHelpText": "Trì hoãn trong vài phút để đợi trước khi lấy một torrent",
    "Torrents": "Torrents",
    "TorrentsDisabled": "Torrents bị vô hiệu hóa",
    "TotalSpace": "Tổng không gian",
    "TpdbIdExcludeHelpText": "Id TMDb của phim để loại trừ",
    "Trace": "Dấu vết",
    "Type": "Kiểu",
    "Ui": "Giao diện người dùng",
    "Wiki": "Wiki",
    "Year": "Năm",
    "Yes": "Đúng",
    "YesCancel": "Có, Hủy bỏ",
    "Dates": "ngày",
    "AddRootFolder": "Thêm thư mục gốc",
    "AllResultsAreHiddenByTheAppliedFilter": "Tất cả kết quả bị ẩn bởi bộ lọc được áp dụng",
    "LastUsed": "Được sử dụng lần cuối",
    "LastWriteTime": "Lần viết cuối cùng",
    "LibraryImport": "Nhập thư viện",
    "LogFiles": "Tệp nhật ký",
    "Debug": "Gỡ lỗi",
    "Reload": "Nạp lại",
    "RemotePath": "Đường đi từ xa",
    "Required": "Cần thiết",
    "About": "Trong khoảng",
    "Actions": "Hành động",
    "Logs": "Nhật ký",
    "Restart": "Khởi động lại",
    "RestartReloadNote": "Lưu ý: Lidarr sẽ tự động khởi động lại và tải lại giao diện người dùng trong quá trình khôi phục.",
    "AutoTaggingNegateHelpText": "Nếu được chọn, định dạng tùy chỉnh sẽ không áp dụng nếu điều kiện {0} này phù hợp.",
    "DeleteTag": "Xóa thẻ",
    "DeleteDownloadClientMessageText": "Bạn có chắc chắn muốn xóa cấu hình chất lượng không {0}",
    "DeleteImportListMessageText": "Bạn có chắc chắn muốn xóa cấu hình chất lượng không {0}",
    "DeleteNotificationMessageText": "Bạn có chắc chắn muốn xóa cấu hình chất lượng không {0}",
    "DeleteSpecificationHelpText": "Bạn có chắc chắn muốn xóa cấu hình chất lượng không {0}",
    "UpdateAutomaticallyHelpText": "Tự động tải xuống và cài đặt các bản cập nhật. Bạn vẫn có thể cài đặt từ Hệ thống: Cập nhật",
    "UpdateMechanismHelpText": "Sử dụng trình cập nhật tích hợp của Lidarr hoặc một tập lệnh",
    "Updates": "Cập nhật",
    "NoIssuesWithYourConfiguration": "Không có vấn đề với cấu hình của bạn",
    "NoLeaveIt": "Không để nó",
    "NoLogFiles": "Không có tệp nhật ký",
    "Peers": "Ngang hàng",
    "RemoveSelectedItemQueueMessageText": "Bạn có chắc chắn muốn xóa {0} khỏi hàng đợi không?",
    "RemoveSelectedItemsQueueMessageText": "Bạn có chắc chắn muốn xóa {0} khỏi hàng đợi không?",
    "DefaultDelayProfile": "Đây là cấu hình mặc định. Nó áp dụng cho tất cả các phim không có hồ sơ rõ ràng.",
    "DelayProfilesLoadError": "Không thể tải hồ sơ độ trễ",
    "Delete": "Xóa bỏ",
    "NoTagsHaveBeenAddedYet": "Chưa có thẻ nào được thêm vào",
    "SetPermissionsLinuxHelpTextWarning": "Nếu bạn không chắc chắn những cài đặt này có tác dụng gì, đừng thay đổi chúng.",
    "SetTags": "Đặt thẻ",
    "ShortDateFormat": "Định dạng ngày ngắn",
    "ShowRelativeDates": "Hiển thị Ngày tương đối",
    "AppDataLocationHealthCheckMessage": "Việc cập nhật sẽ không xảy ra để tránh xóa AppData khi cập nhật",
    "Details": "Chi tiết",
    "AddConditionError": "Không thể thêm điều kiện mới, vui lòng thử lại.",
    "AddCustomFormat": "Thêm định dạng tùy chỉnh",
    "AddCustomFormatError": "Không thể thêm định dạng tùy chỉnh mới, vui lòng thử lại.",
    "AddDelayProfile": "Thêm cấu hình trễ",
    "AddDownloadClient": "Thêm ứng dụng khách tải xuống",
    "AddDownloadClientError": "Không thể thêm ứng dụng khách tải xuống mới, vui lòng thử lại.",
    "AddExclusion": "Thêm loại trừ",
    "AddImportListExclusion": "Xóa loại trừ danh sách nhập",
    "AddImportListExclusionError": "Không thể thêm loại trừ danh sách mới, vui lòng thử lại.",
    "AddIndexer": "Thêm trình lập chỉ mục",
    "AddIndexerError": "Không thể thêm trình chỉ mục mới, vui lòng thử lại.",
    "AddList": "Thêm vào danh sách",
    "AddListError": "Không thể thêm danh sách mới, vui lòng thử lại.",
    "AddListExclusionError": "Không thể thêm loại trừ danh sách mới, vui lòng thử lại.",
    "AddNewRestriction": "Thêm hạn chế mới",
    "AddNewSiteError": "Không tải được kết quả tìm kiếm, vui lòng thử lại.",
    "AddNewSiteHelpText": "Thật dễ dàng để thêm phim mới, chỉ cần bắt đầu nhập tên phim bạn muốn thêm",
    "AddNewSiteRootFolderHelpText": "Thư mục con '{0}' sẽ được tạo tự động",
    "AddNotificationError": "Không thể thêm thông báo mới, vui lòng thử lại.",
    "AddQualityProfile": "Thêm hồ sơ chất lượng",
    "AddQualityProfileError": "Không thể thêm hồ sơ chất lượng mới, vui lòng thử lại.",
    "AddRemotePathMappingError": "Không thể thêm ánh xạ đường dẫn từ xa mới, vui lòng thử lại.",
    "AfterManualRefresh": "Sau khi làm mới thủ công",
    "AlreadyInYourLibrary": "Đã có trong thư viện của bạn",
    "Always": "Luôn luôn",
    "AnalyseVideoFiles": "Phân tích tệp video",
    "AnalyseVideoFilesHelpText": "Trích xuất thông tin video như độ phân giải, thời gian chạy và thông tin codec từ các tệp. Điều này yêu cầu Radarr đọc các phần của tệp có thể gây ra hoạt động mạng hoặc đĩa cao trong quá trình quét.",
    "Analytics": "phân tích",
    "AnalyticsEnabledHelpText": "Gửi thông tin sử dụng và lỗi ẩn danh đến máy chủ của Radarr. Điều này bao gồm thông tin về trình duyệt của bạn, trang WebUI của Radarr mà bạn sử dụng, báo cáo lỗi cũng như hệ điều hành và phiên bản thời gian chạy. Chúng tôi sẽ sử dụng thông tin này để ưu tiên các tính năng và sửa lỗi.",
    "ApiKey": "Mã API",
    "ApplyChanges": "Áp dụng thay đổi",
    "ApplyTagsHelpTextHowToApplyIndexers": "Cách áp dụng thẻ cho các phim đã chọn",
    "ApplyTagsHelpTextHowToApplySeries": "Cách áp dụng thẻ cho các phim đã chọn",
    "ApplyTagsHelpTextReplace": "Thay thế: Thay thế các thẻ bằng các thẻ đã nhập (không nhập thẻ nào để xóa tất cả các thẻ)",
    "AptUpdater": "Sử dụng apt để cài đặt bản cập nhật",
    "AuthBasic": "Cơ bản (Cửa sổ bật lên trình duyệt)",
    "AuthForm": "Biểu mẫu (Trang đăng nhập)",
    "Authentication": "Xác thực",
    "AuthenticationMethodHelpText": "Yêu cầu Tên người dùng và Mật khẩu để truy cập Lidarr",
    "AutoRedownloadFailedHelpText": "Tự động tìm kiếm và cố gắng tải xuống một bản phát hành khác",
    "Automatic": "Tự động",
    "AutomaticAdd": "Tự động thêm",
    "AutomaticSearch": "Tìm kiếm tự động",
    "BackupFolderHelpText": "Các đường dẫn tương đối sẽ nằm trong thư mục AppData của Lidarr",
    "BackupIntervalHelpText": "Khoảng thời gian giữa các bản sao lưu tự động",
    "BackupRetentionHelpText": "Các bản sao lưu tự động cũ hơn khoảng thời gian lưu giữ sẽ tự động được dọn dẹp",
    "BackupsLoadError": "Không thể tải các bản sao lưu",
    "BindAddress": "Địa chỉ ràng buộc",
    "BlocklistLoadError": "Không thể tải danh sách đen",
    "BlocklistRelease": "Chặn bản phát hành",
    "Branch": "Chi nhánh",
    "BranchUpdate": "Nhánh sử dụng để cập nhật Lidarr",
    "BranchUpdateMechanism": "Nhánh được sử dụng bởi cơ chế cập nhật bên ngoài",
    "BrowserReloadRequired": "Yêu cầu tải lại trình duyệt",
    "BuiltIn": "Được xây dựng trong",
    "BypassDelayIfAboveCustomFormatScoreMinimumScore": "Điểm định dạng tùy chỉnh tối thiểu",
    "BypassDelayIfHighestQuality": "Bỏ qua nếu chất lượng cao nhất",
    "BypassProxyForLocalAddresses": "Bỏ qua proxy cho địa chỉ cục bộ",
    "CalendarLoadError": "Không thể tải lịch",
    "CancelProcessing": "Hủy xử lý",
    "CertificateValidation": "Xác thực chứng chỉ",
    "ChangeFileDate": "Thay đổi ngày tệp",
    "ChangeFileDateHelpText": "Thay đổi ngày tệp khi nhập / quét lại",
    "ChmodFolder": "Thư mục chmod",
    "ChmodFolderHelpText": "Hệ bát phân, được áp dụng trong quá trình nhập / đổi tên cho các thư mục và tệp phương tiện (không có bit thực thi)",
    "ChmodFolderHelpTextWarning": "Điều này chỉ hoạt động nếu người dùng chạy Lidarr là chủ sở hữu của tệp. Tốt hơn là đảm bảo ứng dụng khách tải xuống đặt các quyền đúng cách.",
    "ChooseAnotherFolder": "Chọn một thư mục khác",
    "ChownGroupHelpText": "Tên nhóm hoặc gid. Sử dụng gid cho các hệ thống tệp từ xa.",
    "ChownGroupHelpTextWarning": "Điều này chỉ hoạt động nếu người dùng chạy Lidarr là chủ sở hữu của tệp. Tốt hơn là đảm bảo rằng ứng dụng khách tải xuống sử dụng cùng một nhóm với Lidarr.",
    "ClientPriority": "Ưu tiên khách hàng",
    "CloneIndexer": "Trình lập chỉ mục nhân bản",
    "CloneProfile": "Hồ sơ nhân bản",
    "ColonReplacement": "Thay thế ruột kết",
    "ColonReplacementFormatHelpText": "Thay đổi cách Radarr xử lý thay thế dấu hai chấm",
    "CompletedDownloadHandling": "Đã hoàn thành xử lý tải xuống",
    "Condition": "Điều kiện",
    "ConditionUsingRegularExpressions": "Điều kiện này phù hợp với việc sử dụng Biểu thức chính quy. Lưu ý rằng các ký tự {0} có ý nghĩa đặc biệt và cần thoát bằng {1}",
    "Conditions": "Điều kiện",
    "ConnectSettings": "Kết nối Cài đặt",
    "ConnectSettingsSummary": "Thông báo, kết nối với máy chủ / trình phát đa phương tiện và tập lệnh tùy chỉnh",
    "Connections": "Kết nối",
    "CopyToClipboard": "Sao chép vào clipboard",
    "CopyUsingHardlinksHelpTextWarning": "Đôi khi, khóa tệp có thể ngăn đổi tên các tệp đang được seed. Bạn có thể tạm thời tắt tính năng seeding và sử dụng chức năng đổi tên của Lidarr như một công việc xung quanh.",
    "CouldNotFindResults": "Không thể tìm thấy bất kỳ kết quả nào cho '{0}'",
    "CreateEmptySiteFoldersHelpText": "Tạo thư mục phim bị thiếu trong quá trình quét đĩa",
    "CreateGroup": "Tạo nhóm",
    "CurrentlyInstalled": "Mới cài đặt",
    "Custom": "Tập quán",
    "CustomFormat": "Định dạng tùy chỉnh",
    "DownloadClientsSettingsSummary": "Tải xuống ứng dụng khách, xử lý tải xuống và ánh xạ đường dẫn từ xa",
    "DownloadPropersAndRepacks": "Người ủng hộ và người đóng gói",
    "CustomFormatHelpText": "Radarr chấm điểm mỗi bản phát hành bằng cách sử dụng tổng điểm để phù hợp với các định dạng tùy chỉnh. Nếu một bản phát hành mới sẽ cải thiện điểm số, với chất lượng tương đương hoặc tốt hơn, thì Radarr sẽ lấy nó.",
    "CustomFormatScore": "Điểm định dạng tùy chỉnh",
    "CustomFormats": "Định dạng tùy chỉnh",
    "CustomFormatsLoadError": "Không thể tải các Định dạng Tùy chỉnh",
    "CustomFormatsSettings": "Cài đặt định dạng tùy chỉnh",
    "CustomFormatsSettingsSummary": "Định dạng và Cài đặt Tùy chỉnh",
    "Cutoff": "Cắt",
    "CutoffUnmet": "Cắt bỏ chưa được đáp ứng",
    "DeleteAutoTagHelpText": "Bạn có chắc chắn muốn xóa cấu hình chất lượng không {0}",
    "DeleteDelayProfile": "Xóa hồ sơ độ trễ",
    "DeleteDelayProfileMessageText": "Bạn có chắc chắn muốn xóa hồ sơ trì hoãn này không?",
    "DeleteDownloadClient": "Xóa ứng dụng khách tải xuống",
    "DeleteEmptyFolders": "Xóa các thư mục trống",
    "DeleteEmptyFoldersHelpText": "Xóa các thư mục phim trống trong khi quét đĩa và khi các tệp phim bị xóa",
    "DeleteImportListExclusion": "Xóa loại trừ danh sách nhập",
    "DeleteImportListExclusionMessageText": "Bạn có chắc chắn muốn xóa loại trừ danh sách nhập này không?",
    "DeleteIndexer": "Xóa trình lập chỉ mục",
    "DeleteIndexerMessageText": "Xóa trình lập chỉ mục",
    "DeleteNotification": "Xóa thông báo",
    "DeleteQualityProfile": "Xóa hồ sơ chất lượng",
    "DeleteQualityProfileMessageText": "Bạn có chắc chắn muốn xóa cấu hình chất lượng không {0}",
    "DeleteReleaseProfile": "Xóa hồ sơ độ trễ",
    "DeleteReleaseProfileMessageText": "Bạn có chắc chắn muốn xóa cấu hình chất lượng không {0}",
    "DeleteRemotePathMapping": "Chỉnh sửa ánh xạ đường dẫn từ xa",
    "DeleteSpecification": "Xóa thông báo",
    "DeleteTagMessageText": "Bạn có chắc chắn muốn xóa thẻ '{0}' không?",
    "Disabled": "Tàn tật",
    "DisabledForLocalAddresses": "Bị vô hiệu hóa đối với địa chỉ địa phương",
    "Discord": "Bất hòa",
    "DiskSpace": "Dung lượng đĩa",
    "DoNotPrefer": "Không thích",
    "DoNotUpgradeAutomatically": "Không nâng cấp tự động",
    "DoneEditingGroups": "Chỉnh sửa xong nhóm",
    "DownloadClientOptionsLoadError": "Không thể tải các tùy chọn ứng dụng khách tải xuống",
    "DownloadClientSettings": "Tải xuống cài đặt ứng dụng khách",
    "DownloadClientStatusAllClientHealthCheckMessage": "Tất cả các ứng dụng khách tải xuống không khả dụng do lỗi",
    "DownloadClientsLoadError": "Không thể tải ứng dụng khách tải xuống",
    "DownloadPropersAndRepacksHelpText": "Có tự động nâng cấp lên Propers / Repacks hay không",
    "DownloadPropersAndRepacksHelpTextCustomFormat": "Sử dụng 'Không thích' để sắp xếp theo điểm định dạng tùy chỉnh trên Đề xuất / Gói lại",
    "DownloadPropersAndRepacksHelpTextWarning": "Sử dụng các định dạng tùy chỉnh để tự động nâng cấp lên Người ủng hộ / Đóng gói lại",
    "EditCustomFormat": "Chỉnh sửa định dạng tùy chỉnh",
    "EditDelayProfile": "Chỉnh sửa hồ sơ độ trễ",
    "EditGroups": "Chỉnh sửa nhóm",
    "EditImportListExclusion": "Xóa loại trừ danh sách nhập",
    "EditIndexer": "Chỉnh sửa trình lập chỉ mục",
    "EditListExclusion": "Chỉnh sửa Loại trừ Danh sách",
    "EditQualityProfile": "Chỉnh sửa hồ sơ chất lượng",
    "EditRemotePathMapping": "Chỉnh sửa ánh xạ đường dẫn từ xa",
    "EditRestriction": "Chỉnh sửa hạn chế",
    "Enable": "Kích hoạt",
    "EnableAutomaticAdd": "Bật tính năng Thêm tự động",
    "EnableAutomaticSearchHelpText": "Sẽ được sử dụng khi tìm kiếm tự động được thực hiện qua giao diện người dùng hoặc bằng Lidarr",
    "EnableAutomaticSearchHelpTextWarning": "Sẽ được sử dụng khi tìm kiếm tương tác được sử dụng",
    "EnableColorImpairedMode": "Bật Chế độ Khuyết màu",
    "EnableColorImpairedModeHelpText": "Đã thay đổi kiểu để cho phép người dùng khiếm thị phân biệt rõ hơn thông tin mã màu",
    "EnableCompletedDownloadHandlingHelpText": "Tự động nhập các bản tải xuống đã hoàn thành từ máy khách tải xuống",
    "EnableHelpText": "Cho phép tạo tệp siêu dữ liệu cho loại siêu dữ liệu này",
    "EnableInteractiveSearch": "Bật tìm kiếm tương tác",
    "EnableInteractiveSearchHelpText": "Sẽ được sử dụng khi tìm kiếm tương tác được sử dụng",
    "EnableInteractiveSearchHelpTextWarning": "Trình lập chỉ mục này không hỗ trợ tìm kiếm",
    "EnableMediaInfoHelpText": "Trích xuất thông tin video như độ phân giải, thời gian chạy và thông tin codec từ các tệp. Điều này yêu cầu Radarr đọc các phần của tệp có thể gây ra hoạt động mạng hoặc đĩa cao trong quá trình quét.",
    "EnableMetadataHelpText": "Cho phép tạo tệp siêu dữ liệu cho loại siêu dữ liệu này",
    "EnableRss": "Bật RSS",
    "EnableSsl": "Bật SSL",
    "EnableSslHelpText": "Yêu cầu khởi động lại chạy với tư cách quản trị viên để có hiệu lực",
    "Enabled": "Đã bật",
    "Ended": "Đã kết thúc",
    "EpisodeSearchResultsLoadError": "Không thể tải kết quả cho tìm kiếm phim này. Thử lại sau",
    "Events": "Sự kiện",
    "Existing": "Hiện có",
    "ExportCustomFormat": "Xuất định dạng tùy chỉnh",
    "ExternalUpdater": "Radarr được định cấu hình để sử dụng cơ chế cập nhật bên ngoài",
    "ExtraFileExtensionsHelpText": "Danh sách các tệp bổ sung cần nhập được phân tách bằng dấu phẩy (.nfo sẽ được nhập dưới dạng .nfo-orig)",
    "ExtraFileExtensionsHelpTextsExamples": "Ví dụ: '.sub, .nfo' hoặc 'sub, nfo'",
    "Failed": "Thất bại",
    "FeatureRequests": "Yêu cầu tính năng",
    "FileManagement": "Quản lý tệp",
    "FileNameTokens": "Mã thông báo tên tệp",
    "FileNames": "Tên tệp",
    "Filename": "Tên tệp",
    "FirstDayOfWeek": "Ngày đầu tuần",
    "Fixed": "đã sửa",
    "Folder": "Thư mục",
    "Folders": "Thư mục",
    "Formats": "Định dạng",
    "FreeSpace": "Không gian trông",
    "General": "Chung",
    "GeneralSettings": "Cài đặt chung",
    "GeneralSettingsLoadError": "Không thể tải Cài đặt chung",
    "GeneralSettingsSummary": "Cổng, SSL, tên người dùng / mật khẩu, proxy, phân tích và cập nhật",
    "Genres": "Thể loại",
    "Grabbed": "Nắm lấy",
    "Group": "Nhóm",
    "Here": "đây",
    "HistoryLoadError": "Không thể tải lịch sử",
    "Host": "Tổ chức",
    "Hostname": "Tên máy chủ",
    "HttpHttps": "HTTP (S)",
    "IgnoredAddresses": "Địa chỉ bị Bỏ qua",
    "Images": "Hình ảnh",
    "Import": "Nhập khẩu",
    "ImportCustomFormat": "Nhập định dạng tùy chỉnh",
    "ImportErrors": "Nhập lỗi",
    "ImportExistingSites": "Nhập phim hiện có",
    "ImportExtraFiles": "Nhập tệp bổ sung",
    "ImportExtraFilesHelpText": "Nhập các tệp bổ sung phù hợp (phụ đề, nfo, v.v.) sau khi nhập tệp phim",
    "ImportListExclusions": "Xóa loại trừ danh sách nhập",
    "ImportListExclusionsLoadError": "Không thể tải Danh sách Loại trừ",
    "Monitor": "Giám sát",
    "ImportMechanismHandlingDisabledHealthCheckMessage": "Bật Xử lý Tải xuống Đã Hoàn tất",
    "Importing": "Nhập khẩu",
    "IncludeCustomFormatWhenRenaming": "Bao gồm định dạng tùy chỉnh khi đổi tên",
    "IncludeCustomFormatWhenRenamingHelpText": "Bao gồm trong định dạng đổi tên {Custom Formats}",
    "IncludeHealthWarnings": "Bao gồm các cảnh báo về sức khỏe",
    "IndexerLongTermStatusAllUnavailableHealthCheckMessage": "Tất cả các trình lập chỉ mục không khả dụng do lỗi trong hơn 6 giờ",
    "IndexerLongTermStatusUnavailableHealthCheckMessage": "Trình lập chỉ mục không khả dụng do lỗi trong hơn 6 giờ: {0}",
    "IndexerOptionsLoadError": "Không thể tải các tùy chọn trình lập chỉ mục",
    "IndexerPriority": "Mức độ ưu tiên của người lập chỉ mục",
    "IndexerPriorityHelpText": "Mức độ ưu tiên của người lập chỉ mục từ 1 (Cao nhất) đến 50 (Thấp nhất). Mặc định: 25.",
    "IndexerRssNoIndexersAvailableHealthCheckMessage": "Tất cả các trình chỉ mục hỗ trợ rss tạm thời không khả dụng do các lỗi trình lập chỉ mục gần đây",
    "IndexerRssNoIndexersEnabledHealthCheckMessage": "Không có bộ lập chỉ mục nào có đồng bộ RSS được bật, Lidarr sẽ không tự động lấy các bản phát hành mới",
    "IndexerSearchNoAutomaticHealthCheckMessage": "Không có trình chỉ mục nào có sẵn khi bật Tìm kiếm tự động, Lidarr sẽ không cung cấp bất kỳ kết quả tìm kiếm tự động nào",
    "IndexerSearchNoAvailableIndexersHealthCheckMessage": "Tất cả các trình chỉ mục có khả năng tìm kiếm tạm thời không khả dụng do các lỗi trình lập chỉ mục gần đây",
    "IndexerSettings": "Cài đặt trình lập chỉ mục",
    "IndexerStatusUnavailableHealthCheckMessage": "Trình lập chỉ mục không khả dụng do lỗi: {0}",
    "IndexersLoadError": "Không thể tải Trình chỉ mục",
    "InstallLatest": "Cài đặt mới nhất",
    "InteractiveImport": "Nhập tương tác",
    "InteractiveSearch": "Tìm kiếm tương tác",
    "Interval": "Khoảng thời gian",
    "InvalidFormat": "Định dạng không hợp lệ",
    "LastExecution": "Lần thực hiện cuối cùng",
    "LibraryImportTips": "Một số mẹo để đảm bảo quá trình nhập diễn ra suôn sẻ:",
    "LibraryImportTipsDontUseDownloadsFolder": "Không sử dụng để nhập tải xuống từ ứng dụng khách tải xuống của bạn, điều này chỉ dành cho các thư viện có tổ chức hiện có, không phải tệp không được sắp xếp.",
    "ListExclusionsLoadError": "Không thể tải Danh sách Loại trừ",
    "ListsLoadError": "Không thể tải danh sách",
    "LocalPath": "Đường dẫn địa phương",
    "LogLevel": "Mức đăng nhập",
    "LogLevelTraceHelpTextWarning": "Ghi nhật ký theo dõi chỉ nên được bật tạm thời",
    "Logging": "Ghi nhật ký",
    "LongDateFormat": "Định dạng ngày dài",
    "MaintenanceRelease": "Bản phát hành bảo trì: sửa lỗi và các cải tiến khác. Xem Lịch sử cam kết Github để biết thêm chi tiết",
    "ManualImportItemsLoadError": "Không thể tải các mục nhập thủ công",
    "Max": "Max",
    "MaximumLimits": "Giới hạn tối đa",
    "MaximumSize": "Kích thước tối đa",
    "MaximumSizeHelpText": "Kích thước tối đa cho một bản phát hành được tính bằng MB. Đặt thành 0 để đặt thành không giới hạn",
    "Mechanism": "Cơ chế",
    "MediaInfo": "Thông tin truyền thông",
    "MediaManagementSettings": "Cài đặt quản lý phương tiện",
    "MediaManagementSettingsLoadError": "Không thể tải cài đặt Quản lý phương tiện",
    "MegabytesPerMinute": "Megabyte mỗi phút",
    "MetadataLoadError": "Không thể tải Siêu dữ liệu",
    "MetadataSettings": "Cài đặt siêu dữ liệu",
    "Min": "Min",
    "MinimumAge": "Tuổi tối thiểu",
    "MinimumAgeHelpText": "Usenet only: Tuổi tối thiểu tính bằng phút của NZB trước khi chúng bị tóm. Sử dụng điều này để cho các bản phát hành mới có thời gian phổ biến tới nhà cung cấp mạng sử dụng của bạn.",
    "MinimumCustomFormatScore": "Điểm định dạng tùy chỉnh tối thiểu",
    "MinimumCustomFormatScoreHelpText": "Điểm định dạng tùy chỉnh tối thiểu được phép tải xuống",
    "MinimumFreeSpace": "Dung lượng trống tối thiểu",
    "MinimumFreeSpaceHelpText": "Ngăn nhập nếu nó để lại ít hơn số lượng không gian đĩa khả dụng này",
    "MinimumLimits": "Giới hạn tối thiểu",
    "Mode": "Chế độ",
    "Monday": "Thứ hai",
    "MonitorNone": "không ai",
    "Monitored": "Giám sát",
    "MonitoredOnly": "Chỉ giám sát",
    "MoreDetails": "Thêm chi tiết",
    "MoreInfo": "Thêm thông tin",
    "MountHealthCheckMessage": "Mount chứa đường dẫn phim được mount ở chế độ chỉ đọc: ",
    "MoveAutomatically": "Nhập nhanh",
    "MustContain": "Phải chứa",
    "MustContainHelpText": "Bản phát hành phải chứa ít nhất một trong các điều khoản này (không phân biệt chữ hoa chữ thường)",
    "MustNotContain": "Không được chứa",
    "MustNotContainHelpText": "Bản phát hành sẽ bị từ chối nếu nó chứa một hoặc nhiều điều khoản (không phân biệt chữ hoa chữ thường)",
    "Name": "Tên",
    "NamingSettings": "Cài đặt đặt tên",
    "NamingSettingsLoadError": "Không thể tải cài đặt Đặt tên",
    "Negate": "Phủ nhận",
    "NegateHelpText": "Nếu được chọn, định dạng tùy chỉnh sẽ không áp dụng nếu điều kiện {0} này phù hợp.",
    "Negated": "Được tôn trọng",
    "New": "Mới",
    "NextExecution": "Thực hiện tiếp theo",
    "No": "Không",
    "NoBackupsAreAvailable": "Không có bản sao lưu nào",
    "NoChange": "Không thay đổi",
    "NoChanges": "Không thay đổi",
    "NoLimitForAnyRuntime": "Không có giới hạn cho bất kỳ thời gian chạy nào",
    "NoLinks": "Không có liên kết",
    "NoMatchFound": "Không tìm thấy kết quả phù hợp!",
    "NoMinimumForAnyRuntime": "Không có tối thiểu cho bất kỳ thời gian chạy nào",
    "TestAllLists": "Kiểm tra tất cả danh sách",
    "OnEpisodeFileDeleteForUpgrade": "Trên tệp phim, xóa để nâng cấp",
    "OnGrab": "Trên Grab",
    "OnHealthIssue": "Về vấn đề sức khỏe",
    "OnImport": "Khi nhập khẩu",
    "OnRename": "Khi đổi tên",
    "OnUpgrade": "Đang nâng cấp",
    "OnlyTorrent": "Chỉ Torrent",
    "OnlyUsenet": "Chỉ Usenet",
    "OpenBrowserOnStart": "Mở trình duyệt khi bắt đầu",
    "OpenBrowserOnStartHelpText": " Mở trình duyệt web và điều hướng đến trang chủ Radarr khi khởi động ứng dụng.",
    "Original": "Nguyên",
    "OutputPath": "Đường đầu ra",
    "PackageVersion": "Phiên bản gói",
    "Password": "Mật khẩu",
    "PendingChangesDiscardChanges": "Hủy các thay đổi và rời khỏi",
    "PendingChangesMessage": "Bạn có các thay đổi chưa được lưu, bạn có chắc chắn muốn rời khỏi trang này không?",
    "PendingChangesStayReview": "Ở lại và xem xét các thay đổi",
    "Permissions": "Quyền",
    "PortNumber": "Số cổng",
    "PreferAndUpgrade": "Ưu tiên và nâng cấp",
    "PreferTorrent": "Thích Torrent",
    "PreferUsenet": "Ưu tiên Usenet",
    "Preferred": "Ưu tiên",
    "PreferredSize": "Kích thước ưa thích",
    "Presets": "Cài đặt trước",
    "Priority": "Sự ưu tiên",
    "PriorityHelpText": "Ưu tiên nhiều Khách hàng tải xuống. Round-Robin được sử dụng cho các khách hàng có cùng mức độ ưu tiên.",
    "ProcessingFolders": "Xử lý thư mục",
    "Profiles": "Hồ sơ",
    "Progress": "Phát triển",
    "Proper": "Thích hợp",
    "Protocol": "Giao thức",
    "ReleaseTitle": "Tiêu đề phát hành",
    "ProtocolHelpText": "Chọn (các) giao thức để sử dụng và giao thức nào được ưu tiên khi lựa chọn giữa các bản phát hành ngang nhau",
    "Proxy": "Ủy quyền",
    "ProxyBadRequestHealthCheckMessage": "Không thể kiểm tra proxy. Mã trạng thái: {0}",
    "ProxyBypassFilterHelpText": "Sử dụng ',' làm dấu phân tách và '*.' làm ký tự đại diện cho các miền phụ",
    "ProxyFailedToTestHealthCheckMessage": "Không thể kiểm tra proxy: {0}",
    "ProxyPasswordHelpText": "Bạn chỉ cần nhập tên người dùng và mật khẩu nếu được yêu cầu. Nếu không, hãy để trống chúng.",
    "ProxyType": "Loại proxy",
    "ProxyUsernameHelpText": "Bạn chỉ cần nhập tên người dùng và mật khẩu nếu được yêu cầu. Nếu không, hãy để trống chúng.",
    "Qualities": "Phẩm chất",
    "Time": "Thời gian",
    "QualitiesHelpText": "Các phẩm chất cao hơn trong danh sách được ưu tiên hơn. Các phẩm chất trong cùng một nhóm là ngang nhau. Chỉ những phẩm chất đã được kiểm tra mới được mong muốn",
    "QualitiesLoadError": "Không thể tải chất lượng",
    "QualityDefinitions": "Định nghĩa chất lượng",
    "QualityDefinitionsLoadError": "Không thể tải Định nghĩa chất lượng",
    "QualityProfiles": "Hồ sơ chất lượng",
    "QualityProfilesLoadError": "Không thể tải Hồ sơ chất lượng",
    "QualitySettings": "Cài đặt chất lượng",
    "QualitySettingsSummary": "Kích thước chất lượng và cách đặt tên",
    "ReadTheWikiForMoreInformation": "Đọc Wiki để biết thêm thông tin",
    "RecyclingBin": "Thùng tái chế",
    "RecyclingBinCleanup": "Thu dọn thùng rác tái chế",
    "RecyclingBinCleanupHelpText": "Đặt thành 0 để tắt tính năng dọn dẹp tự động",
    "RecyclingBinCleanupHelpTextWarning": "Các tệp trong thùng rác cũ hơn số ngày đã chọn sẽ tự động được dọn dẹp",
    "RecyclingBinHelpText": "Các tệp phim sẽ chuyển đến đây khi bị xóa thay vì bị xóa vĩnh viễn",
    "RedownloadFailed": "Tải xuống không thành công",
    "Refresh": "Làm tươi",
    "RejectionCount": "Số lượng từ chối",
    "RelativePath": "Đường dẫn tương đối",
    "Release": "Phát hành",
    "ReleaseGroup": "Nhóm phát hành",
    "ReleaseGroups": "Nhóm phát hành",
    "ReleaseProfilesLoadError": "Không thể tải hồ sơ độ trễ",
    "RemotePathMappingHostHelpText": "Cùng một máy chủ lưu trữ mà bạn đã chỉ định cho Máy khách tải xuống từ xa",
    "RemotePathMappingLocalPathHelpText": "Đường dẫn mà Lidarr nên sử dụng để truy cập cục bộ đường dẫn từ xa",
    "RemotePathMappingRemotePathHelpText": "Đường dẫn gốc đến thư mục mà Ứng dụng khách tải xuống truy cập",
    "RemotePathMappings": "Ánh xạ đường dẫn từ xa",
    "RemotePathMappingsLoadError": "Không thể tải Ánh xạ đường dẫn từ xa",
    "Remove": "Tẩy",
    "RemoveCompletedDownloadsHelpText": "Xóa các bản tải xuống đã nhập khỏi lịch sử tải xuống của ứng dụng khách",
    "RemoveFailedDownloadsHelpText": "Xóa các lần tải xuống không thành công khỏi lịch sử máy khách tải xuống",
    "RemoveFromDownloadClientHelpTextWarning": "Việc xóa sẽ xóa phần tải xuống và (các) tệp khỏi ứng dụng khách tải xuống.",
    "RemoveRootFolder": "Xóa thư mục gốc",
    "RemovedFromTaskQueue": "Đã xóa khỏi hàng đợi tác vụ",
    "RenameEpisodesHelpText": "Lidarr sẽ sử dụng tên tệp hiện có nếu việc đổi tên bị tắt",
    "Reorder": "Sắp xếp lại",
    "Replace": "Thay thế",
    "ReplaceIllegalCharacters": "Thay thế các ký tự bất hợp pháp",
    "ReplaceIllegalCharactersHelpText": "Thay thế các ký tự bất hợp pháp. Nếu không được chọn, Lidarr sẽ xóa chúng thay thế",
    "ReplaceWithDash": "Thay thế bằng Dấu gạch ngang",
    "ReplaceWithSpaceDash": "Thay thế bằng Dấu gạch ngang",
    "ReplaceWithSpaceDashSpace": "Thay thế bằng Space Dash Space",
    "RescanAfterRefreshHelpText": "Quét lại thư mục phim sau khi làm mới phim",
    "RescanAfterRefreshHelpTextWarning": "Radarr sẽ không tự động phát hiện các thay đổi đối với tệp khi không được đặt thành 'Luôn luôn'",
    "RescanSiteFolderAfterRefresh": "Quét lại thư mục phim sau khi làm mới",
    "Reset": "Cài lại",
    "ResetAPIKey": "Đặt lại khóa API",
    "ResetAPIKeyMessageText": "Bạn có chắc chắn muốn đặt lại Khóa API của mình không?",
    "RestartLater": "Tôi sẽ khởi động lại sau",
    "RestartNow": "Khởi động lại ngay",
    "RestartRequiredHelpTextWarning": "Yêu cầu khởi động lại để có hiệu lực",
    "Restore": "Khôi phục",
    "RestoreBackup": "Khôi phục lại bản sao lưu",
    "RestrictionsLoadError": "Không thể tải Hạn chế",
    "Result": "Kết quả",
    "Retention": "Giữ lại",
    "RetentionHelpText": "Chỉ sử dụng mạng: Đặt thành 0 để đặt giữ chân không giới hạn",
    "RootFolder": "Thư mục gốc",
    "RootFolderLoadError": "Không thể tải các thư mục gốc",
    "RootFolderMissingHealthCheckMessage": "Thiếu thư mục gốc: {0}",
    "RootFolderMultipleMissingHealthCheckMessage": "Nhiều thư mục gốc bị thiếu: {0}",
    "RootFolders": "Thư mục gốc",
    "RootFoldersLoadError": "Không thể tải các thư mục gốc",
    "Rss": "RSS",
    "RssIsNotSupportedWithThisIndexer": "RSS không được hỗ trợ với trình chỉ mục này",
    "RssSyncInterval": "Khoảng thời gian đồng bộ hóa RSS",
    "RssSyncIntervalHelpText": "Khoảng thời gian tính bằng phút. Đặt thành 0 để tắt (điều này sẽ dừng tất cả việc lấy bản phát hành tự động)",
    "RssSyncIntervalHelpTextWarning": "Điều này sẽ áp dụng cho tất cả người lập chỉ mục, vui lòng tuân theo các quy tắc do họ đặt ra",
    "Runtime": "Thời gian chạy",
    "Save": "Tiết kiệm",
    "SaveChanges": "Lưu thay đổi",
    "SaveSettings": "Lưu các thiết lập",
    "Scheduled": "Lên kế hoạch",
    "Score": "Ghi bàn",
    "Script": "Kịch bản",
    "ScriptPath": "Đường dẫn tập lệnh",
    "SearchByTpdbId": "Bạn cũng có thể tìm kiếm bằng cách sử dụng TMDb Id của một bộ phim. ví dụ. 'tmdb: 71663'",
    "SearchFailedError": "Tìm kiếm không thành công, vui lòng thử lại sau.",
    "SearchIsNotSupportedWithThisIndexer": "Trình lập chỉ mục này không hỗ trợ tìm kiếm",
    "ShowRelativeDatesHelpText": "Hiển thị ngày tương đối (Hôm nay / Hôm qua / v.v.) hoặc ngày tuyệt đối",
    "SitesLoadError": "Không thể tải danh sách",
    "SizeOnDisk": "Kích thước trên đĩa",
    "SkipFreeSpaceCheck": "Bỏ qua kiểm tra dung lượng trống",
    "SkipFreeSpaceCheckWhenImportingHelpText": "Sử dụng khi Radarr không thể phát hiện dung lượng trống từ thư mục gốc phim của bạn",
    "Socks4": "Vớ4",
    "Socks5": "Socks5 (Hỗ trợ TOR)",
    "SomeResultsAreHiddenByTheAppliedFilter": "Một số kết quả bị ẩn bởi bộ lọc được áp dụng",
    "Source": "Nguồn",
    "SourceTitle": "Tiêu đề nguồn",
    "SslCertPassword": "Mật khẩu cảnh báo SSL",
    "SslCertPasswordHelpText": "Mật khẩu cho tệp pfx",
    "SslCertPath": "Đường dẫn cảnh báo SSL",
    "SslCertPathHelpText": "Đường dẫn đến tệp pfx",
    "SslPort": "Cổng SSL",
    "StartImport": "Bắt đầu nhập",
    "StartProcessing": "Bắt đầu xử lý",
    "Style": "Phong cách",
    "Sunday": "chủ nhật",
    "SupportedCustomConditions": "Radarr hỗ trợ các điều kiện tùy chỉnh dựa trên các thuộc tính phát hành bên dưới.",
    "SupportedDownloadClients": "Whisparr hỗ trợ bất kỳ ứng dụng khách tải xuống nào sử dụng tiêu chuẩn Newznab, cũng như các ứng dụng khách tải xuống khác được liệt kê bên dưới.",
    "SupportedDownloadClientsMoreInfo": "Để biết thêm thông tin về các ứng dụng khách tải xuống riêng lẻ, hãy nhấp vào các nút thông tin.",
    "SupportedImportListsMoreInfo": "Để biết thêm thông tin về các danh sách nhập riêng lẻ, hãy nhấp vào các nút thông tin.",
    "SupportedIndexers": "Lidarr hỗ trợ bất kỳ trình chỉ mục nào sử dụng tiêu chuẩn Newznab, cũng như các trình chỉ mục khác được liệt kê bên dưới.",
    "SupportedIndexersMoreInfo": "Để biết thêm thông tin về các chỉ mục riêng lẻ, hãy nhấp vào các nút thông tin.",
    "SupportedListsMoreInfo": "Để biết thêm thông tin về các danh sách nhập riêng lẻ, hãy nhấp vào các nút thông tin.",
    "SystemTimeHealthCheckMessage": "Thời gian hệ thống tắt hơn 1 ngày. Các tác vụ đã lên lịch có thể không chạy chính xác cho đến khi thời gian được sửa",
    "TagCannotBeDeletedWhileInUse": "Không thể bị xóa khi đang sử dụng",
    "TagIsNotUsedAndCanBeDeleted": "Thẻ không được sử dụng và có thể bị xóa",
    "TagsLoadError": "Không thể tải thẻ",
    "TagsSettingsSummary": "Xem tất cả các thẻ và cách chúng được sử dụng. Các thẻ không sử dụng có thể bị xóa",
    "Tasks": "Nhiệm vụ",
    "TestAll": "Kiểm tra tất cả",
    "TestAllClients": "Kiểm tra tất cả khách hàng",
    "TestAllIndexers": "Kiểm tra tất cả các chỉ mục",
    "UnableToLoadRootFolders": "Không thể tải các thư mục gốc",
    "UnableToUpdateWhisparrDirectly": "Không thể cập nhật Radarr trực tiếp,",
    "Unavailable": "Không có sẵn",
    "Ungroup": "Bỏ nhóm",
    "Unlimited": "Vô hạn",
    "UnmappedFolders": "Thư mục chưa được ánh xạ",
    "UnmonitorDeletedEpisodesHelpText": "Phim bị xóa khỏi đĩa sẽ tự động không được theo dõi trong Radarr",
    "UnmonitoredOnly": "Chỉ giám sát",
    "UnsavedChanges": "Các thay đổi chưa được lưu",
    "UpdateScriptPathHelpText": "Đường dẫn đến tập lệnh tùy chỉnh có gói cập nhật được trích xuất và xử lý phần còn lại của quá trình cập nhật",
    "UpdateWhisparrDirectlyLoadError": "Không thể cập nhật Radarr trực tiếp,",
    "UpdateStartupTranslocationHealthCheckMessage": "Không thể cài đặt bản cập nhật vì thư mục khởi động '{0}' nằm trong thư mục Chuyển vị ứng dụng.",
    "UpdateUINotWritableHealthCheckMessage": "Không thể cài đặt bản cập nhật vì thư mục giao diện người dùng '{0}' không thể ghi bởi người dùng '{1}'.",
    "UpdateUiNotWritableHealthCheckMessage": "Không thể cài đặt bản cập nhật vì thư mục giao diện người dùng '{0}' không thể ghi bởi người dùng '{1}'.",
    "UpgradeUntilCustomFormatScore": "Nâng cấp cho đến khi điểm định dạng tùy chỉnh",
    "UpgradeUntilCustomFormatScoreHelpText": "Khi đạt đến điểm định dạng tùy chỉnh này, Lidarr sẽ không tải phim xuống nữa",
    "UpgradeUntilHelpText": "Khi đạt đến chất lượng này Lidarr sẽ không tải phim nữa",
    "UpgradeUntilThisQualityIsMetOrExceeded": "Nâng cấp cho đến khi đáp ứng hoặc vượt quá chất lượng này",
    "UpgradesAllowed": "Nâng cấp được phép",
    "UpgradesAllowedHelpText": "Nếu chất lượng bị vô hiệu hóa sẽ không được nâng cấp",
    "Uptime": "Thời gian hoạt động",
    "UrlBase": "Cơ sở URL",
    "UrlBaseHelpText": "Đối với hỗ trợ proxy ngược, mặc định là trống",
    "UseHardlinksInsteadOfCopy": "Sử dụng liên kết cứng thay vì sao chép",
    "UseProxy": "Sử dụng Proxy",
    "Usenet": "Usenet",
    "UsenetDelay": "Sự chậm trễ của Usenet",
    "UsenetDelayHelpText": "Trì hoãn vài phút để đợi trước khi lấy bản phát hành từ Usenet",
    "UsenetDisabled": "Usenet bị vô hiệu hóa",
    "Username": "tên tài khoản",
    "Version": "Phiên bản",
    "VideoCodec": "Codec video",
    "VisitTheWikiForMoreDetails": "Truy cập wiki để biết thêm chi tiết: ",
    "Wanted": "Muốn",
    "WeekColumnHeader": "Tiêu đề cột tuần",
    "WeekColumnHeaderHelpText": "Được hiển thị phía trên mỗi cột khi tuần là chế độ xem đang hoạt động",
    "WhyCantIFindMySite": "Tại sao tôi không thể tìm thấy phim của mình?"
}
